{"v":"5.9.0","fr":24,"ip":0,"op":132,"w":500,"h":500,"nm":"Comp 1","ddd":0,"assets":[{"id":"comp_0","nm":"Pre-comp 1","fr":24,"layers":[{"ddd":0,"ind":1,"ty":4,"nm":"ë6","parent":6,"sr":1,"ks":{"o":{"a":1,"k":[{"i":{"x":[0.833],"y":[0.833]},"o":{"x":[0.167],"y":[0.167]},"t":77,"s":[0]},{"t":82,"s":[100]}],"ix":11},"r":{"a":0,"k":16.918,"ix":10},"p":{"a":1,"k":[{"t":78,"s":[0.137,-94.403,0],"h":1},{"t":80,"s":[5.754,-102.748,0],"h":1},{"t":83,"s":[8.488,-90.18,0],"h":1},{"t":86,"s":[3.658,-102.059,0],"h":1},{"t":89,"s":[0.087,-83.243,0],"h":1},{"t":92,"s":[0.837,-95.097,0],"h":1},{"t":95,"s":[7.071,-85.304,0],"h":1},{"t":98,"s":[0.137,-94.403,0],"h":1},{"t":100,"s":[5.754,-102.748,0],"h":1},{"t":103,"s":[8.488,-90.18,0],"h":1},{"t":106,"s":[3.658,-102.059,0],"h":1},{"t":109,"s":[0.087,-83.243,0],"h":1},{"t":112,"s":[0.837,-95.097,0],"h":1},{"t":115,"s":[7.071,-85.304,0],"h":1},{"t":118,"s":[0.137,-94.403,0],"h":1},{"t":120,"s":[5.754,-102.748,0],"h":1},{"t":123,"s":[8.488,-90.18,0],"h":1},{"t":126,"s":[3.658,-102.059,0],"h":1},{"t":129,"s":[0.087,-83.243,0],"h":1},{"t":132,"s":[0.837,-95.097,0],"h":1},{"t":145,"s":[7.071,-85.304,0],"h":1}],"ix":2,"l":2},"a":{"a":0,"k":[-30.614,-92.389,0],"ix":1,"l":2},"s":{"a":1,"k":[{"t":78,"s":[100,100,100],"h":1},{"t":80,"s":[154.406,93.824,100],"h":1},{"t":82,"s":[140.242,124.599,100],"h":1},{"t":85,"s":[92.996,76.297,100],"h":1},{"t":88,"s":[82.051,135.71,100],"h":1},{"t":90,"s":[102.12,73.126,100],"h":1},{"t":92,"s":[100,100,100],"h":1},{"t":94,"s":[154.406,93.824,100],"h":1},{"t":96,"s":[140.242,124.599,100],"h":1},{"t":99,"s":[92.996,76.297,100],"h":1},{"t":102,"s":[82.051,135.71,100],"h":1},{"t":104,"s":[46.158,44.898,100],"h":1},{"t":107,"s":[100,100,100],"h":1},{"t":109,"s":[154.406,93.824,100],"h":1},{"t":111,"s":[140.242,124.599,100],"h":1},{"t":114,"s":[92.996,76.297,100],"h":1},{"t":117,"s":[82.051,135.71,100],"h":1},{"t":119,"s":[46.158,44.898,100],"h":1},{"t":121,"s":[100,100,100],"h":1},{"t":123,"s":[154.406,93.824,100],"h":1},{"t":125,"s":[140.242,124.599,100],"h":1},{"t":128,"s":[92.996,76.297,100],"h":1},{"t":131,"s":[82.051,135.71,100],"h":1},{"t":133,"s":[46.158,44.898,100],"h":1},{"t":145,"s":[100,100,100],"h":1}],"ix":6,"l":2}},"ao":0,"shapes":[{"ty":"gr","it":[{"ind":0,"ty":"sh","ix":1,"ks":{"a":0,"k":{"i":[[-2.125,-7.084],[4.167,-1.25],[2.125,7.084],[-4.167,1.25]],"o":[[2.125,7.084],[-4.167,1.25],[-2.125,-7.084],[4.167,-1.25]],"v":[[-23.069,-94.652],[-26.766,-79.561],[-38.16,-90.125],[-34.463,-105.216]],"c":true},"ix":2},"nm":"Path 1","mn":"ADBE Vector Shape - Group","hd":false},{"ty":"fl","c":{"a":0,"k":[0,0,0,1],"ix":4},"o":{"a":0,"k":100,"ix":5},"r":1,"bm":0,"nm":"Fill 1","mn":"ADBE Vector Graphic - Fill","hd":false},{"ty":"tr","p":{"a":0,"k":[0,0],"ix":2},"a":{"a":0,"k":[0,0],"ix":1},"s":{"a":0,"k":[100,100],"ix":3},"r":{"a":0,"k":0,"ix":6},"o":{"a":0,"k":100,"ix":7},"sk":{"a":0,"k":0,"ix":4},"sa":{"a":0,"k":0,"ix":5},"nm":"Transform"}],"nm":"Group 1","np":2,"cix":2,"bm":0,"ix":1,"mn":"ADBE Vector Group","hd":false}],"ip":0,"op":144,"st":0,"bm":0},{"ddd":0,"ind":2,"ty":4,"nm":"ë5","parent":6,"sr":1,"ks":{"o":{"a":1,"k":[{"i":{"x":[0.833],"y":[0.833]},"o":{"x":[0.167],"y":[0.167]},"t":77,"s":[0]},{"t":82,"s":[100]}],"ix":11},"r":{"a":0,"k":14.934,"ix":10},"p":{"a":1,"k":[{"t":78,"s":[-70.862,-94.249,0],"h":1},{"t":80,"s":[-77.093,-104.739,0],"h":1},{"t":83,"s":[-61.779,-97.696,0],"h":1},{"t":86,"s":[-76.455,-91.484,0],"h":1},{"t":89,"s":[-61.798,-93.511,0],"h":1},{"t":92,"s":[-76.455,-91.484,0],"h":1},{"t":95,"s":[-65.239,-103.989,0],"h":1},{"t":98,"s":[-70.862,-94.249,0],"h":1},{"t":100,"s":[-77.093,-104.739,0],"h":1},{"t":103,"s":[-61.779,-97.696,0],"h":1},{"t":106,"s":[-76.455,-91.484,0],"h":1},{"t":109,"s":[-61.798,-93.511,0],"h":1},{"t":112,"s":[-76.455,-91.484,0],"h":1},{"t":115,"s":[-65.239,-103.989,0],"h":1},{"t":118,"s":[-70.862,-94.249,0],"h":1},{"t":120,"s":[-77.093,-104.739,0],"h":1},{"t":123,"s":[-61.779,-97.696,0],"h":1},{"t":126,"s":[-76.455,-91.484,0],"h":1},{"t":129,"s":[-61.798,-93.511,0],"h":1},{"t":132,"s":[-76.455,-91.484,0],"h":1},{"t":145,"s":[-65.239,-103.989,0],"h":1}],"ix":2,"l":2},"a":{"a":0,"k":[-86.284,-75.583,0],"ix":1,"l":2},"s":{"a":1,"k":[{"t":78,"s":[100,100,100],"h":1},{"t":80,"s":[171.298,134.284,100],"h":1},{"t":82,"s":[66.437,77.679,100],"h":1},{"t":85,"s":[144.756,52.278,100],"h":1},{"t":88,"s":[108.164,130.462,100],"h":1},{"t":90,"s":[116.31,70.777,100],"h":1},{"t":92,"s":[100,100,100],"h":1},{"t":94,"s":[171.298,134.284,100],"h":1},{"t":96,"s":[66.437,77.679,100],"h":1},{"t":99,"s":[144.756,52.278,100],"h":1},{"t":102,"s":[108.164,130.462,100],"h":1},{"t":104,"s":[108.726,47.346,100],"h":1},{"t":107,"s":[100,100,100],"h":1},{"t":109,"s":[171.298,134.284,100],"h":1},{"t":111,"s":[66.437,77.679,100],"h":1},{"t":114,"s":[144.756,52.278,100],"h":1},{"t":117,"s":[108.164,130.462,100],"h":1},{"t":119,"s":[108.726,47.346,100],"h":1},{"t":121,"s":[100,100,100],"h":1},{"t":123,"s":[171.298,134.284,100],"h":1},{"t":125,"s":[66.437,77.679,100],"h":1},{"t":128,"s":[144.756,52.278,100],"h":1},{"t":131,"s":[108.164,130.462,100],"h":1},{"t":133,"s":[108.726,47.346,100],"h":1}],"ix":6,"l":2}},"ao":0,"shapes":[{"ty":"gr","it":[{"ind":0,"ty":"sh","ix":1,"ks":{"a":0,"k":{"i":[[-2.125,-7.084],[4.167,-1.25],[2.125,7.084],[-4.167,1.25]],"o":[[2.125,7.084],[-4.167,1.25],[-2.125,-7.084],[4.167,-1.25]],"v":[[-78.738,-77.847],[-82.435,-62.755],[-93.829,-73.319],[-90.132,-88.41]],"c":true},"ix":2},"nm":"Path 1","mn":"ADBE Vector Shape - Group","hd":false},{"ty":"fl","c":{"a":0,"k":[0,0,0,1],"ix":4},"o":{"a":0,"k":100,"ix":5},"r":1,"bm":0,"nm":"Fill 1","mn":"ADBE Vector Graphic - Fill","hd":false},{"ty":"tr","p":{"a":0,"k":[0,0],"ix":2},"a":{"a":0,"k":[0,0],"ix":1},"s":{"a":0,"k":[100,100],"ix":3},"r":{"a":0,"k":0,"ix":6},"o":{"a":0,"k":100,"ix":7},"sk":{"a":0,"k":0,"ix":4},"sa":{"a":0,"k":0,"ix":5},"nm":"Transform"}],"nm":"Group 1","np":2,"cix":2,"bm":0,"ix":1,"mn":"ADBE Vector Group","hd":false}],"ip":0,"op":144,"st":0,"bm":0},{"ddd":0,"ind":5,"ty":4,"nm":"ì 2","parent":10,"sr":1,"ks":{"o":{"a":1,"k":[{"i":{"x":[0.833],"y":[0.833]},"o":{"x":[0.167],"y":[0.167]},"t":77,"s":[0]},{"t":82,"s":[100]}],"ix":11},"r":{"a":0,"k":-3.407,"ix":10},"p":{"a":0,"k":[-1.154,-36.244,0],"ix":2,"l":2},"a":{"a":0,"k":[-36.653,-38.582,0],"ix":1,"l":2},"s":{"a":1,"k":[{"i":{"x":[0.667,0.667,0.667],"y":[1,1,1]},"o":{"x":[0.333,0.333,0.333],"y":[0,0,0]},"t":82,"s":[75.03,75.03,100]},{"i":{"x":[0.667,0.667,0.667],"y":[1,1,1]},"o":{"x":[0.333,0.333,0.333],"y":[0,0,0]},"t":85.942,"s":[75.03,106.468,100]},{"i":{"x":[0.667,0.667,0.667],"y":[1,1,1]},"o":{"x":[0.333,0.333,0.333],"y":[0,0,0]},"t":90,"s":[92.644,106.468,100]},{"i":{"x":[0.667,0.667,0.667],"y":[1,1,1]},"o":{"x":[0.333,0.333,0.333],"y":[0,0,0]},"t":93.827,"s":[75.03,106.468,100]},{"i":{"x":[0.667,0.667,0.667],"y":[1,1,1]},"o":{"x":[0.333,0.333,0.333],"y":[0,0,0]},"t":99,"s":[91.859,75.03,100]},{"i":{"x":[0.667,0.667,0.667],"y":[1,1,1]},"o":{"x":[0.333,0.333,0.333],"y":[0,0,0]},"t":101.712,"s":[75.03,106.468,100]},{"i":{"x":[0.667,0.667,0.667],"y":[1,1,1]},"o":{"x":[0.333,0.333,0.333],"y":[0,0,0]},"t":106,"s":[95.53,75.03,100]},{"i":{"x":[0.667,0.667,0.667],"y":[1,1,1]},"o":{"x":[0.333,0.333,0.333],"y":[0,0,0]},"t":108.808,"s":[75.03,106.468,100]},{"i":{"x":[0.667,0.667,0.667],"y":[1,1,1]},"o":{"x":[0.333,0.333,0.333],"y":[0,0,0]},"t":111.962,"s":[75.03,75.03,100]},{"i":{"x":[0.667,0.667,0.667],"y":[1,1,1]},"o":{"x":[0.333,0.333,0.333],"y":[0,0,0]},"t":115.115,"s":[75.03,106.468,100]},{"i":{"x":[0.667,0.667,0.667],"y":[1,1,1]},"o":{"x":[0.333,0.333,0.333],"y":[0,0,0]},"t":119,"s":[113.144,106.468,100]},{"i":{"x":[0.833,0.833,0.833],"y":[1,1,1]},"o":{"x":[0.167,0.167,0.167],"y":[0,0,0]},"t":123,"s":[75.03,106.468,100]},{"i":{"x":[0.833,0.833,0.833],"y":[1,1,1]},"o":{"x":[0.167,0.167,0.167],"y":[0,0,0]},"t":127,"s":[106.16,70.749,100]},{"t":132,"s":[72.287,125.416,100]}],"ix":6,"l":2}},"ao":0,"shapes":[{"ty":"gr","it":[{"ind":0,"ty":"sh","ix":1,"ks":{"a":0,"k":{"i":[[-9.917,2.24],[-0.355,-0.022],[-3.44,1.327],[-3.135,0.661],[-1.254,-0.522],[-7.898,2.888],[-4.962,-0.579],[-3.416,5.434],[-6.333,-1.048],[-2.95,-0.45],[-4.282,2.257],[-2.416,-4.342],[-0.659,-6.302],[5.156,-3.683],[6.897,-2.707],[5.098,-5.474],[7.441,0.767],[8.019,-1.385],[7.041,-2.012]],"o":[[0.332,-0.075],[3.68,0.224],[2.989,-1.153],[1.329,-0.28],[12.168,5.07],[4.692,-1.715],[6.375,0.744],[3.416,-5.434],[2.943,0.487],[6.267,0.955],[4.396,-2.317],[3.081,5.537],[0.659,6.302],[-6.029,4.306],[-6.963,2.733],[-5.098,5.474],[-8.095,-0.834],[-7.216,1.246],[-23.556,6.731]],"v":[[-93.257,-39.906],[-92.227,-39.988],[-82.527,-35.65],[-76.58,-42.772],[-72.704,-41.769],[-53.446,-52.611],[-39.283,-48.88],[-24.72,-59.78],[-9.973,-70.285],[-1.563,-67.312],[7.908,-76.641],[19.337,-69.675],[25.994,-52.012],[19.471,-35.089],[-1.792,-29.231],[-18.617,-14.709],[-37.846,-4.82],[-60.805,-12.022],[-79.306,-0.634]],"c":true},"ix":2},"nm":"Path 1","mn":"ADBE Vector Shape - Group","hd":false},{"ty":"fl","c":{"a":0,"k":[0,0,0,1],"ix":4},"o":{"a":0,"k":100,"ix":5},"r":1,"bm":0,"nm":"Fill 1","mn":"ADBE Vector Graphic - Fill","hd":false},{"ty":"tr","p":{"a":0,"k":[-35.724,-36.976],"ix":2},"a":{"a":0,"k":[-36.032,-37.183],"ix":1},"s":{"a":0,"k":[100,100],"ix":3},"r":{"a":0,"k":23.076,"ix":6},"o":{"a":0,"k":100,"ix":7},"sk":{"a":0,"k":0,"ix":4},"sa":{"a":0,"k":0,"ix":5},"nm":"Transform"}],"nm":"Group 1","np":2,"cix":2,"bm":0,"ix":1,"mn":"ADBE Vector Group","hd":false}],"ip":82,"op":144,"st":0,"bm":0},{"ddd":0,"ind":6,"ty":4,"nm":"ì","parent":10,"sr":1,"ks":{"o":{"a":1,"k":[{"i":{"x":[0.833],"y":[0.833]},"o":{"x":[0.167],"y":[0.167]},"t":77,"s":[0]},{"t":82,"s":[100]}],"ix":11},"r":{"a":0,"k":-1.595,"ix":10},"p":{"a":0,"k":[-0.728,-40.442,0],"ix":2,"l":2},"a":{"a":0,"k":[-36.653,-38.582,0],"ix":1,"l":2},"s":{"a":0,"k":[75.03,75.03,100],"ix":6,"l":2}},"ao":0,"shapes":[{"ty":"gr","it":[{"ind":0,"ty":"sh","ix":1,"ks":{"a":0,"k":{"i":[[-9.917,2.24],[-0.355,-0.022],[-3.44,1.327],[-3.135,0.661],[-1.254,-0.522],[-7.898,2.888],[-4.962,-0.579],[-3.416,5.434],[-6.333,-1.048],[-2.95,-0.45],[-4.282,2.257],[-2.416,-4.342],[-0.659,-6.302],[5.156,-3.683],[6.897,-2.707],[5.098,-5.474],[7.441,0.767],[8.019,-1.385],[7.041,-2.012]],"o":[[0.332,-0.075],[3.68,0.224],[2.989,-1.153],[1.329,-0.28],[12.168,5.07],[4.692,-1.715],[6.375,0.744],[3.416,-5.434],[2.943,0.487],[6.267,0.955],[4.396,-2.317],[3.081,5.537],[0.659,6.302],[-6.029,4.306],[-6.963,2.733],[-5.098,5.474],[-8.095,-0.834],[-7.216,1.246],[-23.556,6.731]],"v":[[-93.257,-39.906],[-92.227,-39.988],[-82.527,-35.65],[-76.58,-42.772],[-72.704,-41.769],[-53.446,-52.611],[-39.283,-48.88],[-24.72,-59.78],[-9.973,-70.285],[-1.563,-67.312],[7.908,-76.641],[19.337,-69.675],[25.994,-52.012],[19.471,-35.089],[-1.792,-29.231],[-18.617,-14.709],[-37.846,-4.82],[-60.805,-12.022],[-79.306,-0.634]],"c":true},"ix":2},"nm":"Path 1","mn":"ADBE Vector Shape - Group","hd":false},{"ty":"fl","c":{"a":0,"k":[0,0,0,1],"ix":4},"o":{"a":0,"k":100,"ix":5},"r":1,"bm":0,"nm":"Fill 1","mn":"ADBE Vector Graphic - Fill","hd":false},{"ty":"tr","p":{"a":0,"k":[-35.724,-36.976],"ix":2},"a":{"a":0,"k":[-36.032,-37.183],"ix":1},"s":{"a":0,"k":[100,100],"ix":3},"r":{"a":0,"k":23.076,"ix":6},"o":{"a":0,"k":100,"ix":7},"sk":{"a":0,"k":0,"ix":4},"sa":{"a":0,"k":0,"ix":5},"nm":"Transform"}],"nm":"Group 1","np":2,"cix":2,"bm":0,"ix":1,"mn":"ADBE Vector Group","hd":false}],"ip":0,"op":82,"st":0,"bm":0},{"ddd":0,"ind":7,"ty":3,"nm":"Null 2 scale","sr":1,"ks":{"o":{"a":0,"k":0,"ix":11},"r":{"a":1,"k":[{"i":{"x":[0.833],"y":[0.833]},"o":{"x":[0.167],"y":[0.167]},"t":71,"s":[0]},{"t":78,"s":[7.114]}],"ix":10},"p":{"a":1,"k":[{"i":{"x":0.667,"y":0.854},"o":{"x":0.333,"y":0},"t":71,"s":[499,353,0],"to":[4,-29,0],"ti":[0,0,0]},{"i":{"x":0.667,"y":1},"o":{"x":0.333,"y":0.145},"t":78,"s":[520.214,293.002,0],"to":[-20.714,40.998,0],"ti":[0,0,0]},{"i":{"x":0.667,"y":1},"o":{"x":0.167,"y":0},"t":91,"s":[493,409,0],"to":[0,0,0],"ti":[0,0,0]},{"i":{"x":0.667,"y":1},"o":{"x":0.167,"y":0},"t":104,"s":[494,376,0],"to":[0,0,0],"ti":[0,0,0]},{"i":{"x":0.667,"y":1},"o":{"x":0.167,"y":0},"t":120,"s":[493,409,0],"to":[0,0,0],"ti":[0,0,0]},{"t":132,"s":[494,376,0]}],"ix":2,"l":2},"a":{"a":0,"k":[50,50,0],"ix":1,"l":2},"s":{"a":0,"k":[100,100,100],"ix":6,"l":2}},"ao":0,"ip":0,"op":144,"st":0,"bm":0},{"ddd":0,"ind":8,"ty":3,"nm":"Null 3 ì²ìë³´ìê¸° ë¶ëªíë","parent":9,"sr":1,"ks":{"o":{"a":0,"k":0,"ix":11},"r":{"a":0,"k":-152.409,"ix":10},"p":{"a":1,"k":[{"i":{"x":0.034,"y":1},"o":{"x":0.333,"y":0},"t":27,"s":[248.068,-342.112,0],"to":[0,0,0],"ti":[0,0,0]},{"i":{"x":0.667,"y":1},"o":{"x":0.851,"y":0},"t":38,"s":[128.913,-39.354,0],"to":[0,0,0],"ti":[0,0,0]},{"t":51,"s":[182.799,-195.816,0]}],"ix":2,"l":2},"a":{"a":0,"k":[0,0,0],"ix":1,"l":2},"s":{"a":0,"k":[149.635,149.635,100],"ix":6,"l":2}},"ao":0,"ip":0,"op":144,"st":0,"bm":0},{"ddd":0,"ind":9,"ty":3,"nm":"Null 1 rotation","parent":7,"sr":1,"ks":{"o":{"a":0,"k":0,"ix":11},"r":{"a":0,"k":239.607,"ix":10},"p":{"a":1,"k":[{"i":{"x":0.833,"y":0.833},"o":{"x":0.167,"y":0.167},"t":50,"s":[20.745,67.68,0],"to":[0.858,-4.442,0],"ti":[-185.043,-37.978,0]},{"i":{"x":0.833,"y":0.833},"o":{"x":0.167,"y":0.167},"t":54,"s":[240.795,-103.485,0],"to":[185.043,37.978,0],"ti":[144.474,-45.599,0]},{"i":{"x":0.833,"y":0.833},"o":{"x":0.167,"y":0.167},"t":59,"s":[259.848,214.619,0],"to":[-144.474,45.599,0],"ti":[-4.9,84.537,0]},{"t":70,"s":[44.745,28.68,0]}],"ix":2,"l":2},"a":{"a":0,"k":[50,50,0],"ix":1,"l":2},"s":{"a":0,"k":[66.829,66.829,100],"ix":6,"l":2}},"ao":1,"ip":48,"op":165,"st":21,"bm":0},{"ddd":0,"ind":10,"ty":4,"nm":"ë³´ìê¸°","parent":8,"sr":1,"ks":{"o":{"a":0,"k":100,"ix":11},"r":{"a":0,"k":-94.316,"ix":10},"p":{"a":1,"k":[{"i":{"x":0.833,"y":0.833},"o":{"x":0.167,"y":0.167},"t":0,"s":[113.606,-444.516,0],"to":[0,0,0],"ti":[19.012,-75.761,0]},{"i":{"x":0.833,"y":0.833},"o":{"x":0.167,"y":0.167},"t":13,"s":[74.358,-324.318,0],"to":[-19.012,75.761,0],"ti":[0,0,0]},{"t":28,"s":[59.514,-128.769,0]}],"ix":2,"l":2},"a":{"a":0,"k":[22.097,-63.339,0],"ix":1,"l":2},"s":{"a":1,"k":[{"i":{"x":[0.833,0.833,0.833],"y":[0.833,0.833,0.833]},"o":{"x":[0.167,0.167,0.167],"y":[0.167,0.167,0.167]},"t":40,"s":[95.54,95.54,100]},{"i":{"x":[0.833,0.833,0.833],"y":[0.833,0.833,0.833]},"o":{"x":[0.167,0.167,0.167],"y":[0.167,0.167,0.167]},"t":44,"s":[119.671,73.105,100]},{"i":{"x":[0.833,0.833,0.833],"y":[0.833,0.833,0.833]},"o":{"x":[0.167,0.167,0.167],"y":[0.167,0.167,0.167]},"t":50,"s":[119.671,73.105,100]},{"i":{"x":[0.833,0.833,0.833],"y":[0.833,0.833,0.833]},"o":{"x":[0.167,0.167,0.167],"y":[0.167,0.167,0.167]},"t":54,"s":[62.448,114.343,100]},{"i":{"x":[0.833,0.833,0.833],"y":[0.833,0.833,0.833]},"o":{"x":[0.167,0.167,0.167],"y":[0.167,0.167,0.167]},"t":67,"s":[62.448,114.343,100]},{"t":71,"s":[95.54,95.54,100]}],"ix":6,"l":2}},"ao":1,"shapes":[{"ty":"gr","it":[{"ind":0,"ty":"sh","ix":1,"ks":{"a":1,"k":[{"i":{"x":0.833,"y":1},"o":{"x":0.333,"y":0},"t":0,"s":[{"i":[[41.817,23.795],[15.299,32.221],[-12.35,1.378],[-36.475,11.333],[-61.668,-13.351],[-45.257,-0.043],[21.839,-48.255],[32.769,6.641]],"o":[[-13.907,-7.914],[6.405,0.705],[47.971,-5.353],[28.747,-8.931],[44.232,9.576],[-42.633,31.431],[-15.891,-8.475],[-67.166,-13.612]],"v":[[-113.301,-33.146],[-161.284,-88.48],[-132.282,-88.483],[-31.722,-134.328],[70.326,-120.704],[205.477,-110.999],[106.613,11.195],[32.578,-15.562]],"c":true}]},{"i":{"x":0.833,"y":1},"o":{"x":0.167,"y":0},"t":13,"s":[{"i":[[41.166,31.31],[-6.447,37.257],[-17.265,-5.168],[-37.057,-9.252],[-66.255,18.653],[-41.284,25.981],[13.575,-55.71],[32.463,-7.085]],"o":[[-22.945,-17.451],[9.244,11.189],[22.686,6.791],[38.252,9.551],[43.563,-12.265],[-42.633,31.431],[-30.075,-13.144],[-44.851,9.789]],"v":[[-100.035,-30.12],[-153.026,-120.703],[-117.93,-91.486],[-40.233,-85.069],[80.314,-87.375],[200.503,-139.88],[110.67,-2.248],[17.03,5.171]],"c":true}]},{"i":{"x":0.833,"y":1},"o":{"x":0.333,"y":0},"t":24,"s":[{"i":[[41.817,23.795],[15.299,32.221],[-12.35,1.378],[-36.475,11.333],[-61.668,-13.351],[-45.257,-0.043],[21.839,-48.255],[32.769,6.641]],"o":[[-13.907,-7.914],[6.405,0.705],[47.971,-5.353],[28.747,-8.931],[44.232,9.576],[-42.633,31.431],[-15.891,-8.475],[-67.166,-13.612]],"v":[[-113.301,-33.146],[-161.284,-88.48],[-132.282,-88.483],[-31.722,-134.328],[70.326,-120.704],[205.477,-110.999],[106.613,11.195],[32.578,-15.562]],"c":true}]},{"i":{"x":0.833,"y":1},"o":{"x":0.167,"y":0},"t":34,"s":[{"i":[[24.084,64.591],[36.284,15.48],[-5.718,25.483],[-36.475,11.333],[-35.934,-37.727],[-2.106,-46.022],[22.387,14.805],[27.425,0.166]],"o":[[-20.389,-54.683],[-28.36,-12.099],[22.171,-98.804],[28.747,-8.931],[40.674,42.704],[2.578,56.34],[-18.888,-12.491],[-31.199,-0.189]],"v":[[-45.571,139.949],[-116.284,124.52],[-118.282,12.516],[-31.722,-134.328],[72.326,-105.704],[117.301,76.342],[71.212,132.196],[33.642,95.816]],"c":true}]},{"i":{"x":0.833,"y":0.833},"o":{"x":0.167,"y":0},"t":39,"s":[{"i":[[24.084,64.591],[36.284,15.48],[-5.718,25.484],[-36.475,11.333],[-35.934,-37.727],[-2.106,-46.022],[22.387,14.805],[26.221,8.041]],"o":[[-20.389,-54.683],[-28.36,-12.099],[22.171,-98.804],[28.747,-8.931],[40.674,42.704],[2.578,56.34],[-18.888,-12.491],[-25.158,-7.715]],"v":[[-50.296,123.345],[-116.284,124.52],[-118.282,12.516],[-31.722,-134.328],[72.326,-105.704],[117.301,76.342],[83.968,138.068],[29.997,112.69]],"c":true}]},{"i":{"x":0.833,"y":1},"o":{"x":0.167,"y":0.167},"t":44,"s":[{"i":[[47.301,50.146],[36.284,15.48],[-5.718,25.484],[-36.475,11.332],[-35.934,-37.727],[-8.288,-47.801],[22.387,14.805],[26.695,6.288]],"o":[[-28.311,-30.013],[-28.36,-12.099],[22.171,-98.804],[28.747,-8.931],[40.674,42.704],[8.85,45.617],[-18.888,-12.491],[-31.578,-7.439]],"v":[[-45.301,166.484],[-116.284,175.15],[-127.903,54.126],[-31.722,-83.698],[79.843,-53.45],[133.309,110.251],[87.613,171.825],[36.578,140.068]],"c":true}]},{"i":{"x":0.833,"y":1},"o":{"x":0.167,"y":0},"t":50,"s":[{"i":[[47.301,50.146],[36.284,15.48],[-5.718,25.484],[-36.475,11.333],[-35.934,-37.727],[3.646,-54.447],[22.387,14.805],[26.695,6.288]],"o":[[-28.311,-30.013],[-28.36,-12.099],[22.171,-98.804],[28.747,-8.931],[40.674,42.704],[-3.19,47.632],[-18.888,-12.491],[-31.578,-7.439]],"v":[[-45.301,115.854],[-116.284,124.52],[-139.879,-7.732],[-31.722,-134.328],[89.199,-102.059],[145.547,42.968],[87.613,121.195],[36.578,89.438]],"c":true}]},{"i":{"x":0.833,"y":1},"o":{"x":0.167,"y":0},"t":54,"s":[{"i":[[60.882,32.332],[39.331,3.029],[2.5,46.763],[-36.475,11.333],[-8.206,-51.451],[-53.938,-40.349],[25.952,6.845],[27.302,-2.603]],"o":[[-36.439,-19.351],[-30.742,-2.367],[-5.406,-101.116],[28.747,-8.931],[11.651,73.047],[38.227,28.595],[-21.896,-5.775],[-32.295,3.079]],"v":[[35.099,141.748],[-29.357,172.716],[-120.104,18.557],[-31.722,-134.328],[72.326,-105.704],[175.445,50.067],[162.708,104.191],[104.185,90.474]],"c":true}]},{"i":{"x":0.833,"y":1},"o":{"x":0.167,"y":0},"t":66,"s":[{"i":[[60.882,32.332],[39.331,3.029],[2.5,46.763],[-36.475,11.333],[-8.206,-51.451],[-53.938,-40.349],[25.952,6.845],[27.302,-2.603]],"o":[[-36.439,-19.351],[-30.742,-2.367],[-5.406,-101.116],[28.747,-8.931],[11.651,73.047],[38.227,28.595],[-21.896,-5.775],[-32.295,3.079]],"v":[[35.099,141.748],[-29.357,172.716],[-120.104,18.557],[-31.722,-134.328],[72.326,-105.704],[175.445,50.067],[162.708,104.191],[104.185,90.474]],"c":true}]},{"i":{"x":0.833,"y":1},"o":{"x":0.167,"y":0},"t":70,"s":[{"i":[[47.301,50.146],[36.284,15.48],[-5.718,25.484],[-36.475,11.333],[-35.934,-37.727],[-17.876,-42.461],[22.387,14.805],[26.695,6.288]],"o":[[-28.311,-30.013],[-28.36,-12.099],[22.171,-98.804],[28.747,-8.931],[40.674,42.704],[18.523,43.999],[-18.888,-12.491],[-31.578,-7.439]],"v":[[-45.301,115.854],[-116.284,124.52],[-118.282,12.516],[-31.722,-134.328],[72.326,-105.704],[123.477,73.001],[87.613,121.195],[36.578,89.438]],"c":true}]},{"i":{"x":0.833,"y":1},"o":{"x":0.167,"y":0},"t":79,"s":[{"i":[[47.301,50.146],[36.284,15.48],[-4.195,39.498],[-36.475,11.333],[-35.934,-37.727],[5.011,-45.797],[22.387,14.805],[26.695,6.288]],"o":[[-28.311,-30.013],[-28.36,-12.099],[10.696,-100.694],[28.747,-8.931],[40.674,42.704],[-5.565,50.865],[-18.888,-12.491],[-31.578,-7.439]],"v":[[-38.197,106.265],[-95.258,128.216],[-116.067,17.7],[-31.722,-134.328],[72.326,-105.704],[113.086,76.385],[71.917,121.562],[36.578,89.438]],"c":true}]},{"i":{"x":0.833,"y":1},"o":{"x":0.167,"y":0},"t":90,"s":[{"i":[[47.301,50.146],[24.421,40.498],[-5.718,25.484],[-36.475,11.333],[-35.934,-37.727],[-36.351,-44.088],[39.68,13.569],[45.542,-5.966]],"o":[[-28.311,-30.013],[-15.922,-26.404],[22.171,-98.804],[28.747,-8.931],[40.674,42.704],[30.37,36.833],[-21.426,-7.327],[-32.167,4.214]],"v":[[-45.301,115.854],[-148.067,108.512],[-118.282,12.516],[-31.722,-134.328],[72.326,-105.704],[131.799,70.713],[100.365,129.273],[39.062,106.132]],"c":true}]},{"i":{"x":0.833,"y":1},"o":{"x":0.167,"y":0},"t":104,"s":[{"i":[[47.301,50.146],[36.284,15.48],[-5.718,25.484],[-36.475,11.333],[-35.934,-37.727],[-17.876,-42.461],[22.387,14.805],[26.695,6.288]],"o":[[-28.311,-30.013],[-28.36,-12.099],[22.171,-98.804],[28.747,-8.931],[40.674,42.704],[18.523,43.999],[-18.888,-12.491],[-31.578,-7.439]],"v":[[-45.301,115.854],[-116.284,124.52],[-118.282,12.516],[-31.722,-134.328],[72.326,-105.704],[123.477,73.001],[87.613,121.195],[36.578,89.438]],"c":true}]},{"i":{"x":0.833,"y":1},"o":{"x":0.167,"y":0},"t":120,"s":[{"i":[[47.301,50.146],[24.421,40.498],[-5.718,25.484],[-36.475,11.333],[-35.934,-37.727],[-36.351,-44.088],[39.68,13.569],[45.542,-5.966]],"o":[[-28.311,-30.013],[-15.922,-26.404],[22.171,-98.804],[28.747,-8.931],[40.674,42.704],[30.37,36.833],[-21.426,-7.327],[-32.167,4.214]],"v":[[-45.301,115.854],[-148.067,108.512],[-118.282,12.516],[-31.722,-134.328],[72.326,-105.704],[131.799,70.713],[100.365,129.273],[39.062,106.132]],"c":true}]},{"t":132,"s":[{"i":[[47.301,50.146],[36.284,15.48],[-5.718,25.484],[-36.475,11.333],[-35.934,-37.727],[-17.876,-42.461],[22.387,14.805],[26.695,6.288]],"o":[[-28.311,-30.013],[-28.36,-12.099],[22.171,-98.804],[28.747,-8.931],[40.674,42.704],[18.523,43.999],[-18.888,-12.491],[-31.578,-7.439]],"v":[[-45.301,115.854],[-116.284,124.52],[-118.282,12.516],[-31.722,-134.328],[72.326,-105.704],[123.477,73.001],[87.613,121.195],[36.578,89.438]],"c":true}]}],"ix":2},"nm":"Path 1","mn":"ADBE Vector Shape - Group","hd":false},{"ty":"fl","c":{"a":0,"k":[0.96862745285,0.96862745285,0.96862745285,1],"ix":4},"o":{"a":0,"k":100,"ix":5},"r":1,"bm":0,"nm":"Fill 1","mn":"ADBE Vector Graphic - Fill","hd":false},{"ty":"tr","p":{"a":0,"k":[1.092,-0.01],"ix":2},"a":{"a":0,"k":[0,0],"ix":1},"s":{"a":0,"k":[100,100],"ix":3},"r":{"a":0,"k":0,"ix":6},"o":{"a":0,"k":100,"ix":7},"sk":{"a":0,"k":0,"ix":4},"sa":{"a":0,"k":0,"ix":5},"nm":"Transform"}],"nm":"Group 1","np":2,"cix":2,"bm":0,"ix":1,"mn":"ADBE Vector Group","hd":false}],"ip":0,"op":144,"st":0,"bm":0},{"ddd":0,"ind":11,"ty":4,"nm":"blur","parent":10,"sr":1,"ks":{"o":{"a":0,"k":100,"ix":11},"r":{"a":0,"k":-1.34,"ix":10},"p":{"a":0,"k":[-5.752,16.7,0],"ix":2,"l":2},"a":{"a":0,"k":[72,-194,0],"ix":1,"l":2},"s":{"a":1,"k":[{"i":{"x":[0.833,0.833,0.833],"y":[0.833,0.833,0.833]},"o":{"x":[0.167,0.167,0.167],"y":[0.167,0.167,0.167]},"t":76,"s":[36.558,36.558,100]},{"i":{"x":[0.833,0.833,0.833],"y":[0.833,0.833,0.833]},"o":{"x":[0.167,0.167,0.167],"y":[0.167,0.167,0.167]},"t":84,"s":[104.668,104.668,100]},{"i":{"x":[0.833,0.833,0.833],"y":[0.833,0.833,0.833]},"o":{"x":[0.167,0.167,0.167],"y":[0.167,0.167,0.167]},"t":92,"s":[74.377,74.377,100]},{"i":{"x":[0.833,0.833,0.833],"y":[0.833,0.833,0.833]},"o":{"x":[0.167,0.167,0.167],"y":[0.167,0.167,0.167]},"t":100,"s":[104.668,104.668,100]},{"i":{"x":[0.833,0.833,0.833],"y":[0.833,0.833,0.833]},"o":{"x":[0.167,0.167,0.167],"y":[0.167,0.167,0.167]},"t":108,"s":[74.377,74.377,100]},{"i":{"x":[0.833,0.833,0.833],"y":[0.833,0.833,0.833]},"o":{"x":[0.167,0.167,0.167],"y":[0.167,0.167,0.167]},"t":116,"s":[104.668,104.668,100]},{"i":{"x":[0.833,0.833,0.833],"y":[0.833,0.833,0.833]},"o":{"x":[0.167,0.167,0.167],"y":[0.167,0.167,0.167]},"t":124,"s":[74.377,74.377,100]},{"t":132,"s":[104.668,104.668,100]}],"ix":6,"l":2}},"ao":0,"shapes":[{"ty":"gr","it":[{"d":1,"ty":"el","s":{"a":0,"k":[313.047,313.047],"ix":2},"p":{"a":0,"k":[0,0],"ix":3},"nm":"Ellipse Path 1","mn":"ADBE Vector Shape - Ellipse","hd":false},{"ty":"st","c":{"a":0,"k":[0.236396998985,0.900829958448,1,1],"ix":3},"o":{"a":0,"k":100,"ix":4},"w":{"a":0,"k":0,"ix":5},"lc":1,"lj":1,"ml":4,"bm":0,"nm":"Stroke 1","mn":"ADBE Vector Graphic - Stroke","hd":false},{"ty":"gf","o":{"a":0,"k":100,"ix":10},"r":1,"bm":0,"g":{"p":3,"k":{"a":0,"k":[0,0.213,1,0.127,0.5,0.253,1,0.144,1,0.292,1,0.16,0,1,0.468,0.5,1,0],"ix":9}},"s":{"a":0,"k":[0,0],"ix":5},"e":{"a":0,"k":[149.617,6.261],"ix":6},"t":2,"h":{"a":0,"k":0,"ix":7},"a":{"a":0,"k":0,"ix":8},"nm":"Gradient Fill 1","mn":"ADBE Vector Graphic - G-Fill","hd":false},{"ty":"tr","p":{"a":0,"k":[66.289,-199.195],"ix":2},"a":{"a":0,"k":[0,0],"ix":1},"s":{"a":0,"k":[165.943,173.94],"ix":3},"r":{"a":0,"k":22.569,"ix":6},"o":{"a":0,"k":100,"ix":7},"sk":{"a":0,"k":0,"ix":4},"sa":{"a":0,"k":0,"ix":5},"nm":"Transform"}],"nm":"Ellipse 1","np":3,"cix":2,"bm":0,"ix":1,"mn":"ADBE Vector Group","hd":false}],"ip":76,"op":220,"st":76,"bm":0},{"ddd":0,"ind":12,"ty":4,"nm":"í¸ë°","sr":1,"ks":{"o":{"a":0,"k":100,"ix":11},"r":{"a":1,"k":[{"i":{"x":[0.742],"y":[0.997]},"o":{"x":[0.793],"y":[0.01]},"t":0,"s":[83.282]},{"t":36,"s":[613.352]}],"ix":10},"p":{"a":1,"k":[{"i":{"x":0.833,"y":0.833},"o":{"x":0.167,"y":0.167},"t":0,"s":[566.126,787.025,0],"to":[0,0,0],"ti":[0,0,0]},{"i":{"x":0.833,"y":0.833},"o":{"x":0.167,"y":0.167},"t":29,"s":[521.126,528.025,0],"to":[0,0,0],"ti":[0,0,0]},{"t":287,"s":[517.126,721.025,0]}],"ix":2,"l":2},"a":{"a":0,"k":[10.514,125.625,0],"ix":1,"l":2},"s":{"a":0,"k":[100,100,100],"ix":6,"l":2}},"ao":0,"shapes":[{"ty":"gr","it":[{"ty":"gr","it":[{"ind":0,"ty":"sh","ix":1,"ks":{"a":0,"k":{"i":[[0,0],[-0.163,-1.857],[-2.115,-0.32],[-0.41,0.743],[0.479,1.597],[0.283,1.494],[0.448,-0.615]],"o":[[-1.112,1.526],[0.154,1.75],[0.775,0.117],[0.924,-1.677],[-0.438,-1.461],[-0.174,-0.917],[0,0]],"v":[[13.892,81.339],[12.622,86.599],[15.214,91.321],[17.221,90.504],[16.555,86.067],[15.692,81.574],[13.892,81.339]],"c":true},"ix":2},"nm":"Path 1","mn":"ADBE Vector Shape - Group","hd":false},{"ty":"fl","c":{"a":0,"k":[0.32549020648,0.376470595598,0.203921571374,1],"ix":4},"o":{"a":0,"k":100,"ix":5},"r":1,"bm":0,"nm":"Fill 1","mn":"ADBE Vector Graphic - Fill","hd":false},{"ty":"tr","p":{"a":0,"k":[0,0],"ix":2},"a":{"a":0,"k":[0,0],"ix":1},"s":{"a":0,"k":[100,100],"ix":3},"r":{"a":0,"k":0,"ix":6},"o":{"a":0,"k":100,"ix":7},"sk":{"a":0,"k":0,"ix":4},"sa":{"a":0,"k":0,"ix":5},"nm":"Transform"}],"nm":"Group 1","np":2,"cix":2,"bm":0,"ix":1,"mn":"ADBE Vector Group","hd":false},{"ty":"tr","p":{"a":0,"k":[0,0],"ix":2},"a":{"a":0,"k":[0,0],"ix":1},"s":{"a":0,"k":[100,100],"ix":3},"r":{"a":0,"k":0,"ix":6},"o":{"a":0,"k":100,"ix":7},"sk":{"a":0,"k":0,"ix":4},"sa":{"a":0,"k":0,"ix":5},"nm":"Transform"}],"nm":"Group 1","np":1,"cix":2,"bm":0,"ix":1,"mn":"ADBE Vector Group","hd":false},{"ty":"gr","it":[{"ty":"gr","it":[{"ind":0,"ty":"sh","ix":1,"ks":{"a":0,"k":{"i":[[0,0],[1.128,0],[-1.128,0]],"o":[[1.126,0],[-1.126,0],[0,0]],"v":[[17.138,65.831],[17.138,64.081],[17.138,65.831]],"c":true},"ix":2},"nm":"Path 1","mn":"ADBE Vector Shape - Group","hd":false},{"ty":"fl","c":{"a":0,"k":[0.666666686535,0.717647075653,0.54509806633,1],"ix":4},"o":{"a":0,"k":100,"ix":5},"r":1,"bm":0,"nm":"Fill 1","mn":"ADBE Vector Graphic - Fill","hd":false},{"ty":"tr","p":{"a":0,"k":[0,0],"ix":2},"a":{"a":0,"k":[0,0],"ix":1},"s":{"a":0,"k":[100,100],"ix":3},"r":{"a":0,"k":0,"ix":6},"o":{"a":0,"k":100,"ix":7},"sk":{"a":0,"k":0,"ix":4},"sa":{"a":0,"k":0,"ix":5},"nm":"Transform"}],"nm":"Group 1","np":2,"cix":2,"bm":0,"ix":1,"mn":"ADBE Vector Group","hd":false},{"ty":"tr","p":{"a":0,"k":[0,0],"ix":2},"a":{"a":0,"k":[0,0],"ix":1},"s":{"a":0,"k":[100,100],"ix":3},"r":{"a":0,"k":0,"ix":6},"o":{"a":0,"k":100,"ix":7},"sk":{"a":0,"k":0,"ix":4},"sa":{"a":0,"k":0,"ix":5},"nm":"Transform"}],"nm":"Group 2","np":1,"cix":2,"bm":0,"ix":2,"mn":"ADBE Vector Group","hd":false},{"ty":"gr","it":[{"ty":"gr","it":[{"ind":0,"ty":"sh","ix":1,"ks":{"a":0,"k":{"i":[[0,0],[1.128,0],[-1.128,0]],"o":[[1.126,0],[-1.126,0],[0,0]],"v":[[13.45,65.831],[13.45,64.081],[13.45,65.831]],"c":true},"ix":2},"nm":"Path 1","mn":"ADBE Vector Shape - Group","hd":false},{"ty":"fl","c":{"a":0,"k":[0.666666686535,0.717647075653,0.54509806633,1],"ix":4},"o":{"a":0,"k":100,"ix":5},"r":1,"bm":0,"nm":"Fill 1","mn":"ADBE Vector Graphic - Fill","hd":false},{"ty":"tr","p":{"a":0,"k":[0,0],"ix":2},"a":{"a":0,"k":[0,0],"ix":1},"s":{"a":0,"k":[100,100],"ix":3},"r":{"a":0,"k":0,"ix":6},"o":{"a":0,"k":100,"ix":7},"sk":{"a":0,"k":0,"ix":4},"sa":{"a":0,"k":0,"ix":5},"nm":"Transform"}],"nm":"Group 1","np":2,"cix":2,"bm":0,"ix":1,"mn":"ADBE Vector Group","hd":false},{"ty":"tr","p":{"a":0,"k":[0,0],"ix":2},"a":{"a":0,"k":[0,0],"ix":1},"s":{"a":0,"k":[100,100],"ix":3},"r":{"a":0,"k":0,"ix":6},"o":{"a":0,"k":100,"ix":7},"sk":{"a":0,"k":0,"ix":4},"sa":{"a":0,"k":0,"ix":5},"nm":"Transform"}],"nm":"Group 3","np":1,"cix":2,"bm":0,"ix":3,"mn":"ADBE Vector Group","hd":false},{"ty":"gr","it":[{"ty":"gr","it":[{"ind":0,"ty":"sh","ix":1,"ks":{"a":0,"k":{"i":[[0,0],[0.881,0],[-0.881,0]],"o":[[0.88,0],[-0.88,0],[0,0]],"v":[[16.64,67.234],[16.64,65.867],[16.64,67.234]],"c":true},"ix":2},"nm":"Path 1","mn":"ADBE Vector Shape - Group","hd":false},{"ty":"fl","c":{"a":0,"k":[0.666666686535,0.717647075653,0.54509806633,1],"ix":4},"o":{"a":0,"k":100,"ix":5},"r":1,"bm":0,"nm":"Fill 1","mn":"ADBE Vector Graphic - Fill","hd":false},{"ty":"tr","p":{"a":0,"k":[0,0],"ix":2},"a":{"a":0,"k":[0,0],"ix":1},"s":{"a":0,"k":[100,100],"ix":3},"r":{"a":0,"k":0,"ix":6},"o":{"a":0,"k":100,"ix":7},"sk":{"a":0,"k":0,"ix":4},"sa":{"a":0,"k":0,"ix":5},"nm":"Transform"}],"nm":"Group 1","np":2,"cix":2,"bm":0,"ix":1,"mn":"ADBE Vector Group","hd":false},{"ty":"tr","p":{"a":0,"k":[0,0],"ix":2},"a":{"a":0,"k":[0,0],"ix":1},"s":{"a":0,"k":[100,100],"ix":3},"r":{"a":0,"k":0,"ix":6},"o":{"a":0,"k":100,"ix":7},"sk":{"a":0,"k":0,"ix":4},"sa":{"a":0,"k":0,"ix":5},"nm":"Transform"}],"nm":"Group 4","np":1,"cix":2,"bm":0,"ix":4,"mn":"ADBE Vector Group","hd":false},{"ty":"gr","it":[{"ty":"gr","it":[{"ind":0,"ty":"sh","ix":1,"ks":{"a":0,"k":{"i":[[0,0],[-0.121,0.063],[-0.092,0.099],[-0.041,0.125],[0.005,0.139],[0.012,0.09],[0.125,0.126],[0.068,0.053],[0.183,0.001],[0.121,-0.063],[0.092,-0.099],[0.041,-0.125],[-0.005,-0.139],[-0.012,-0.09],[-0.125,-0.126],[-0.068,-0.053],[-0.183,-0.001]],"o":[[0.139,0.005],[0.125,-0.041],[0.099,-0.092],[0.063,-0.121],[-0.012,-0.09],[-0.048,-0.171],[-0.068,-0.053],[-0.158,-0.092],[-0.139,-0.005],[-0.125,0.041],[-0.099,0.092],[-0.063,0.121],[0.012,0.09],[0.048,0.171],[0.068,0.053],[0.158,0.092],[0,0]],"v":[[15.543,62.379],[15.933,62.292],[16.259,62.083],[16.468,61.757],[16.555,61.367],[16.519,61.098],[16.259,60.652],[16.054,60.494],[15.543,60.355],[15.153,60.443],[14.828,60.652],[14.619,60.977],[14.531,61.367],[14.568,61.636],[14.828,62.083],[15.033,62.241],[15.543,62.379]],"c":true},"ix":2},"nm":"Path 1","mn":"ADBE Vector Shape - Group","hd":false},{"ty":"fl","c":{"a":0,"k":[0.666666686535,0.717647075653,0.54509806633,1],"ix":4},"o":{"a":0,"k":100,"ix":5},"r":1,"bm":0,"nm":"Fill 1","mn":"ADBE Vector Graphic - Fill","hd":false},{"ty":"tr","p":{"a":0,"k":[0,0],"ix":2},"a":{"a":0,"k":[0,0],"ix":1},"s":{"a":0,"k":[100,100],"ix":3},"r":{"a":0,"k":0,"ix":6},"o":{"a":0,"k":100,"ix":7},"sk":{"a":0,"k":0,"ix":4},"sa":{"a":0,"k":0,"ix":5},"nm":"Transform"}],"nm":"Group 1","np":2,"cix":2,"bm":0,"ix":1,"mn":"ADBE Vector Group","hd":false},{"ty":"tr","p":{"a":0,"k":[0,0],"ix":2},"a":{"a":0,"k":[0,0],"ix":1},"s":{"a":0,"k":[100,100],"ix":3},"r":{"a":0,"k":0,"ix":6},"o":{"a":0,"k":100,"ix":7},"sk":{"a":0,"k":0,"ix":4},"sa":{"a":0,"k":0,"ix":5},"nm":"Transform"}],"nm":"Group 5","np":1,"cix":2,"bm":0,"ix":5,"mn":"ADBE Vector Group","hd":false},{"ty":"gr","it":[{"ty":"gr","it":[{"ind":0,"ty":"sh","ix":1,"ks":{"a":0,"k":{"i":[[0,0],[-0.014,-0.109],[-0.05,-0.119],[-0.086,-0.083],[-0.086,-0.056],[-0.176,0.057],[-0.118,0.172],[0.076,0.293],[0.028,0.1],[0.414,-0.056],[0.125,-0.136],[-0.026,-0.218]],"o":[[0.013,0.109],[0.016,0.128],[0.046,0.109],[0.073,0.071],[0.155,0.101],[0.197,-0.064],[0.169,-0.246],[-0.026,-0.101],[-0.115,-0.408],[-0.178,0.024],[-0.141,0.154],[0,0]],"v":[[12.702,62.364],[12.741,62.69],[12.819,63.046],[13.013,63.338],[13.263,63.524],[13.853,63.601],[14.31,63.249],[14.451,62.439],[14.367,62.139],[13.437,61.532],[12.95,61.765],[12.702,62.364]],"c":true},"ix":2},"nm":"Path 1","mn":"ADBE Vector Shape - Group","hd":false},{"ty":"fl","c":{"a":0,"k":[0.666666686535,0.717647075653,0.54509806633,1],"ix":4},"o":{"a":0,"k":100,"ix":5},"r":1,"bm":0,"nm":"Fill 1","mn":"ADBE Vector Graphic - Fill","hd":false},{"ty":"tr","p":{"a":0,"k":[0,0],"ix":2},"a":{"a":0,"k":[0,0],"ix":1},"s":{"a":0,"k":[100,100],"ix":3},"r":{"a":0,"k":0,"ix":6},"o":{"a":0,"k":100,"ix":7},"sk":{"a":0,"k":0,"ix":4},"sa":{"a":0,"k":0,"ix":5},"nm":"Transform"}],"nm":"Group 1","np":2,"cix":2,"bm":0,"ix":1,"mn":"ADBE Vector Group","hd":false},{"ty":"tr","p":{"a":0,"k":[0,0],"ix":2},"a":{"a":0,"k":[0,0],"ix":1},"s":{"a":0,"k":[100,100],"ix":3},"r":{"a":0,"k":0,"ix":6},"o":{"a":0,"k":100,"ix":7},"sk":{"a":0,"k":0,"ix":4},"sa":{"a":0,"k":0,"ix":5},"nm":"Transform"}],"nm":"Group 6","np":1,"cix":2,"bm":0,"ix":6,"mn":"ADBE Vector Group","hd":false},{"ty":"gr","it":[{"ty":"gr","it":[{"ind":0,"ty":"sh","ix":1,"ks":{"a":0,"k":{"i":[[0,0],[-0.107,-0.426],[-0.04,0.502],[0.023,0.395],[0.292,0],[-0.031,-0.281]],"o":[[0.048,0.436],[0.134,0.533],[0.031,-0.394],[-0.016,-0.28],[-0.257,0],[0,0]],"v":[[15.025,63.062],[15.196,64.381],[16.109,64.258],[16.064,63.062],[15.544,62.542],[15.025,63.062]],"c":true},"ix":2},"nm":"Path 1","mn":"ADBE Vector Shape - Group","hd":false},{"ty":"fl","c":{"a":0,"k":[0.666666686535,0.717647075653,0.54509806633,1],"ix":4},"o":{"a":0,"k":100,"ix":5},"r":1,"bm":0,"nm":"Fill 1","mn":"ADBE Vector Graphic - Fill","hd":false},{"ty":"tr","p":{"a":0,"k":[0,0],"ix":2},"a":{"a":0,"k":[0,0],"ix":1},"s":{"a":0,"k":[100,100],"ix":3},"r":{"a":0,"k":0,"ix":6},"o":{"a":0,"k":100,"ix":7},"sk":{"a":0,"k":0,"ix":4},"sa":{"a":0,"k":0,"ix":5},"nm":"Transform"}],"nm":"Group 1","np":2,"cix":2,"bm":0,"ix":1,"mn":"ADBE Vector Group","hd":false},{"ty":"tr","p":{"a":0,"k":[0,0],"ix":2},"a":{"a":0,"k":[0,0],"ix":1},"s":{"a":0,"k":[100,100],"ix":3},"r":{"a":0,"k":0,"ix":6},"o":{"a":0,"k":100,"ix":7},"sk":{"a":0,"k":0,"ix":4},"sa":{"a":0,"k":0,"ix":5},"nm":"Transform"}],"nm":"Group 7","np":1,"cix":2,"bm":0,"ix":7,"mn":"ADBE Vector Group","hd":false},{"ty":"gr","it":[{"ty":"gr","it":[{"ind":0,"ty":"sh","ix":1,"ks":{"a":0,"k":{"i":[[0,0],[-0.118,0.02],[-0.07,0.029],[-0.059,0.046],[-0.025,0.19],[0.063,0.149],[0.054,0.055],[0.102,0.055],[0.105,0.08],[0.188,0.001],[0.162,-0.094],[0.092,-0.156],[0.006,-0.138],[-0.043,-0.138],[-0.129,-0.13],[-0.176,-0.049],[-0.184,0.049]],"o":[[0.118,-0.02],[0.07,-0.029],[0.059,-0.046],[0.137,-0.137],[0.022,-0.16],[-0.021,-0.074],[-0.062,-0.095],[-0.105,-0.08],[-0.162,-0.094],[-0.188,0.001],[-0.156,0.092],[-0.076,0.119],[-0.031,0.138],[0.049,0.176],[0.13,0.129],[0.184,0.049],[0,0]],"v":[[12.631,60.669],[12.986,60.611],[13.195,60.522],[13.372,60.386],[13.613,59.883],[13.553,59.43],[13.441,59.237],[13.195,59.011],[12.879,58.77],[12.355,58.628],[11.83,58.77],[11.458,59.143],[11.334,59.529],[11.353,59.943],[11.62,60.402],[12.078,60.669],[12.631,60.669]],"c":true},"ix":2},"nm":"Path 1","mn":"ADBE Vector Shape - Group","hd":false},{"ty":"fl","c":{"a":0,"k":[0.666666686535,0.717647075653,0.54509806633,1],"ix":4},"o":{"a":0,"k":100,"ix":5},"r":1,"bm":0,"nm":"Fill 1","mn":"ADBE Vector Graphic - Fill","hd":false},{"ty":"tr","p":{"a":0,"k":[0,0],"ix":2},"a":{"a":0,"k":[0,0],"ix":1},"s":{"a":0,"k":[100,100],"ix":3},"r":{"a":0,"k":0,"ix":6},"o":{"a":0,"k":100,"ix":7},"sk":{"a":0,"k":0,"ix":4},"sa":{"a":0,"k":0,"ix":5},"nm":"Transform"}],"nm":"Group 1","np":2,"cix":2,"bm":0,"ix":1,"mn":"ADBE Vector Group","hd":false},{"ty":"tr","p":{"a":0,"k":[0,0],"ix":2},"a":{"a":0,"k":[0,0],"ix":1},"s":{"a":0,"k":[100,100],"ix":3},"r":{"a":0,"k":0,"ix":6},"o":{"a":0,"k":100,"ix":7},"sk":{"a":0,"k":0,"ix":4},"sa":{"a":0,"k":0,"ix":5},"nm":"Transform"}],"nm":"Group 8","np":1,"cix":2,"bm":0,"ix":8,"mn":"ADBE Vector Group","hd":false},{"ty":"gr","it":[{"ty":"gr","it":[{"ind":0,"ty":"sh","ix":1,"ks":{"a":0,"k":{"i":[[0,0],[-0.245,-0.213],[-0.324,-0.015],[-0.217,0.281],[0.044,0.324],[0.086,0.135],[0.177,0.105],[0.126,0.094],[-0.074,-0.057],[0.057,0.055],[0.421,-0.325],[-0.254,-0.474]],"o":[[0.153,0.285],[0.245,0.214],[0.367,0.016],[0.2,-0.259],[-0.007,-0.156],[-0.105,-0.177],[-0.144,-0.062],[0.074,0.057],[-0.062,-0.049],[-0.383,-0.371],[-0.427,0.33],[0,0]],"v":[[9.642,61.903],[10.25,62.672],[11.081,63.016],[12.005,62.553],[12.236,61.684],[12.097,61.247],[11.675,60.825],[11.272,60.592],[11.495,60.765],[11.317,60.61],[9.917,60.527],[9.642,61.903]],"c":true},"ix":2},"nm":"Path 1","mn":"ADBE Vector Shape - Group","hd":false},{"ty":"fl","c":{"a":0,"k":[0.666666686535,0.717647075653,0.54509806633,1],"ix":4},"o":{"a":0,"k":100,"ix":5},"r":1,"bm":0,"nm":"Fill 1","mn":"ADBE Vector Graphic - Fill","hd":false},{"ty":"tr","p":{"a":0,"k":[0,0],"ix":2},"a":{"a":0,"k":[0,0],"ix":1},"s":{"a":0,"k":[100,100],"ix":3},"r":{"a":0,"k":0,"ix":6},"o":{"a":0,"k":100,"ix":7},"sk":{"a":0,"k":0,"ix":4},"sa":{"a":0,"k":0,"ix":5},"nm":"Transform"}],"nm":"Group 1","np":2,"cix":2,"bm":0,"ix":1,"mn":"ADBE Vector Group","hd":false},{"ty":"tr","p":{"a":0,"k":[0,0],"ix":2},"a":{"a":0,"k":[0,0],"ix":1},"s":{"a":0,"k":[100,100],"ix":3},"r":{"a":0,"k":0,"ix":6},"o":{"a":0,"k":100,"ix":7},"sk":{"a":0,"k":0,"ix":4},"sa":{"a":0,"k":0,"ix":5},"nm":"Transform"}],"nm":"Group 9","np":1,"cix":2,"bm":0,"ix":9,"mn":"ADBE Vector Group","hd":false},{"ty":"gr","it":[{"ty":"gr","it":[{"ind":0,"ty":"sh","ix":1,"ks":{"a":0,"k":{"i":[[0,0],[0.302,0.062],[0.335,-0.365],[0,-0.363],[-0.243,-0.243],[-0.478,0.097],[-0.302,0.062],[0.021,0.476],[0.506,0.103]],"o":[[-0.302,-0.062],[-0.461,-0.094],[-0.241,0.262],[0,0.344],[0.355,0.355],[0.302,-0.062],[0.472,-0.096],[-0.022,-0.482],[0,0]],"v":[[-2.006,88.442],[-2.914,88.258],[-4.217,88.602],[-4.61,89.55],[-4.217,90.497],[-2.914,90.842],[-2.006,90.657],[-1.163,89.55],[-2.006,88.442]],"c":true},"ix":2},"nm":"Path 1","mn":"ADBE Vector Shape - Group","hd":false},{"ty":"fl","c":{"a":0,"k":[0.32549020648,0.376470595598,0.203921571374,1],"ix":4},"o":{"a":0,"k":100,"ix":5},"r":1,"bm":0,"nm":"Fill 1","mn":"ADBE Vector Graphic - Fill","hd":false},{"ty":"tr","p":{"a":0,"k":[0,0],"ix":2},"a":{"a":0,"k":[0,0],"ix":1},"s":{"a":0,"k":[100,100],"ix":3},"r":{"a":0,"k":0,"ix":6},"o":{"a":0,"k":100,"ix":7},"sk":{"a":0,"k":0,"ix":4},"sa":{"a":0,"k":0,"ix":5},"nm":"Transform"}],"nm":"Group 1","np":2,"cix":2,"bm":0,"ix":1,"mn":"ADBE Vector Group","hd":false},{"ty":"tr","p":{"a":0,"k":[0,0],"ix":2},"a":{"a":0,"k":[0,0],"ix":1},"s":{"a":0,"k":[100,100],"ix":3},"r":{"a":0,"k":0,"ix":6},"o":{"a":0,"k":100,"ix":7},"sk":{"a":0,"k":0,"ix":4},"sa":{"a":0,"k":0,"ix":5},"nm":"Transform"}],"nm":"Group 10","np":1,"cix":2,"bm":0,"ix":10,"mn":"ADBE Vector Group","hd":false},{"ty":"gr","it":[{"ty":"gr","it":[{"ind":0,"ty":"sh","ix":1,"ks":{"a":0,"k":{"i":[[0,0],[-0.832,-2.009],[0.972,-1.386],[1.523,-1.501],[1.152,-3.191],[-0.743,0.895],[-2.905,3.233],[0.022,3.21],[3.542,-3.738],[-0.44,0.328]],"o":[[2.105,-1.567],[0.744,1.796],[-1.234,1.759],[-2.391,2.356],[-0.39,1.081],[2.78,-3.351],[2.064,-2.296],[-0.031,-4.578],[-0.346,0.365],[0,0]],"v":[[4.717,66.071],[9.965,68.31],[8.397,73.702],[3.977,78.37],[-1.703,86.268],[0.262,87.412],[8.962,77.76],[12.867,69.593],[4.154,65.341],[4.717,66.071]],"c":true},"ix":2},"nm":"Path 1","mn":"ADBE Vector Shape - Group","hd":false},{"ty":"fl","c":{"a":0,"k":[0.32549020648,0.376470595598,0.203921571374,1],"ix":4},"o":{"a":0,"k":100,"ix":5},"r":1,"bm":0,"nm":"Fill 1","mn":"ADBE Vector Graphic - Fill","hd":false},{"ty":"tr","p":{"a":0,"k":[0,0],"ix":2},"a":{"a":0,"k":[0,0],"ix":1},"s":{"a":0,"k":[100,100],"ix":3},"r":{"a":0,"k":0,"ix":6},"o":{"a":0,"k":100,"ix":7},"sk":{"a":0,"k":0,"ix":4},"sa":{"a":0,"k":0,"ix":5},"nm":"Transform"}],"nm":"Group 1","np":2,"cix":2,"bm":0,"ix":1,"mn":"ADBE Vector Group","hd":false},{"ty":"tr","p":{"a":0,"k":[0,0],"ix":2},"a":{"a":0,"k":[0,0],"ix":1},"s":{"a":0,"k":[100,100],"ix":3},"r":{"a":0,"k":0,"ix":6},"o":{"a":0,"k":100,"ix":7},"sk":{"a":0,"k":0,"ix":4},"sa":{"a":0,"k":0,"ix":5},"nm":"Transform"}],"nm":"Group 11","np":1,"cix":2,"bm":0,"ix":11,"mn":"ADBE Vector Group","hd":false},{"ty":"gr","it":[{"ty":"gr","it":[{"ind":0,"ty":"sh","ix":1,"ks":{"a":0,"k":{"i":[[0,0],[0.016,0.13],[0.132,0.303],[0.085,0.194],[0.259,-0.591],[0.085,-0.194],[0.041,-0.326],[0.016,-0.13],[-0.207,-0.207],[-0.32,0.014],[0.086,0.715]],"o":[[-0.016,-0.13],[-0.041,-0.326],[-0.085,-0.194],[-0.259,-0.591],[-0.085,0.194],[-0.132,0.303],[-0.016,0.13],[-0.036,0.304],[0.223,0.223],[0.628,-0.028],[0,0]],"v":[[-31.172,181.144],[-31.219,180.754],[-31.423,180.003],[-31.678,179.42],[-33.237,179.42],[-33.492,180.003],[-33.696,180.754],[-33.743,181.144],[-33.366,182.053],[-32.457,182.429],[-31.172,181.144]],"c":true},"ix":2},"nm":"Path 1","mn":"ADBE Vector Shape - Group","hd":false},{"ty":"fl","c":{"a":0,"k":[0.807843148708,0.349019616842,0.137254908681,1],"ix":4},"o":{"a":0,"k":100,"ix":5},"r":1,"bm":0,"nm":"Fill 1","mn":"ADBE Vector Graphic - Fill","hd":false},{"ty":"tr","p":{"a":0,"k":[0,0],"ix":2},"a":{"a":0,"k":[0,0],"ix":1},"s":{"a":0,"k":[100,100],"ix":3},"r":{"a":0,"k":0,"ix":6},"o":{"a":0,"k":100,"ix":7},"sk":{"a":0,"k":0,"ix":4},"sa":{"a":0,"k":0,"ix":5},"nm":"Transform"}],"nm":"Group 1","np":2,"cix":2,"bm":0,"ix":1,"mn":"ADBE Vector Group","hd":false},{"ty":"tr","p":{"a":0,"k":[0,0],"ix":2},"a":{"a":0,"k":[0,0],"ix":1},"s":{"a":0,"k":[100,100],"ix":3},"r":{"a":0,"k":0,"ix":6},"o":{"a":0,"k":100,"ix":7},"sk":{"a":0,"k":0,"ix":4},"sa":{"a":0,"k":0,"ix":5},"nm":"Transform"}],"nm":"Group 12","np":1,"cix":2,"bm":0,"ix":12,"mn":"ADBE Vector Group","hd":false},{"ty":"gr","it":[{"ty":"gr","it":[{"ind":0,"ty":"sh","ix":1,"ks":{"a":0,"k":{"i":[[0,0],[-0.925,-1.894],[-2.173,0.556],[1.046,1.199],[0.631,2.119],[0.292,-1.402]],"o":[[-0.43,2.06],[0.802,1.643],[2.446,-0.626],[-1.451,-1.664],[-0.373,-1.252],[0,0]],"v":[[-43.286,168.719],[-42.471,174.817],[-37.634,178.567],[-37.657,174.164],[-40.597,168.719],[-43.286,168.719]],"c":true},"ix":2},"nm":"Path 1","mn":"ADBE Vector Shape - Group","hd":false},{"ty":"fl","c":{"a":0,"k":[0.807843148708,0.349019616842,0.137254908681,1],"ix":4},"o":{"a":0,"k":100,"ix":5},"r":1,"bm":0,"nm":"Fill 1","mn":"ADBE Vector Graphic - Fill","hd":false},{"ty":"tr","p":{"a":0,"k":[0,0],"ix":2},"a":{"a":0,"k":[0,0],"ix":1},"s":{"a":0,"k":[100,100],"ix":3},"r":{"a":0,"k":0,"ix":6},"o":{"a":0,"k":100,"ix":7},"sk":{"a":0,"k":0,"ix":4},"sa":{"a":0,"k":0,"ix":5},"nm":"Transform"}],"nm":"Group 1","np":2,"cix":2,"bm":0,"ix":1,"mn":"ADBE Vector Group","hd":false},{"ty":"tr","p":{"a":0,"k":[0,0],"ix":2},"a":{"a":0,"k":[0,0],"ix":1},"s":{"a":0,"k":[100,100],"ix":3},"r":{"a":0,"k":0,"ix":6},"o":{"a":0,"k":100,"ix":7},"sk":{"a":0,"k":0,"ix":4},"sa":{"a":0,"k":0,"ix":5},"nm":"Transform"}],"nm":"Group 13","np":1,"cix":2,"bm":0,"ix":13,"mn":"ADBE Vector Group","hd":false},{"ty":"gr","it":[{"ty":"gr","it":[{"ind":0,"ty":"sh","ix":1,"ks":{"a":0,"k":{"i":[[0,0],[-0.346,-0.66],[-0.8,-0.227],[0.767,0.769],[0.125,0.212],[0.065,0.222],[-0.015,0.27],[0.653,0],[0.072,-0.678]],"o":[[-0.079,0.746],[0.393,0.75],[1.055,0.3],[-0.228,-0.229],[-0.079,-0.134],[-0.041,-0.141],[0.037,-0.679],[-0.74,0],[0,0]],"v":[[18.285,183.045],[18.738,185.211],[20.558,186.61],[21.622,184.782],[20.98,183.9],[20.834,183.553],[20.801,183.045],[19.543,181.787],[18.285,183.045]],"c":true},"ix":2},"nm":"Path 1","mn":"ADBE Vector Shape - Group","hd":false},{"ty":"fl","c":{"a":0,"k":[0.807843148708,0.349019616842,0.137254908681,1],"ix":4},"o":{"a":0,"k":100,"ix":5},"r":1,"bm":0,"nm":"Fill 1","mn":"ADBE Vector Graphic - Fill","hd":false},{"ty":"tr","p":{"a":0,"k":[0,0],"ix":2},"a":{"a":0,"k":[0,0],"ix":1},"s":{"a":0,"k":[100,100],"ix":3},"r":{"a":0,"k":0,"ix":6},"o":{"a":0,"k":100,"ix":7},"sk":{"a":0,"k":0,"ix":4},"sa":{"a":0,"k":0,"ix":5},"nm":"Transform"}],"nm":"Group 1","np":2,"cix":2,"bm":0,"ix":1,"mn":"ADBE Vector Group","hd":false},{"ty":"tr","p":{"a":0,"k":[0,0],"ix":2},"a":{"a":0,"k":[0,0],"ix":1},"s":{"a":0,"k":[100,100],"ix":3},"r":{"a":0,"k":0,"ix":6},"o":{"a":0,"k":100,"ix":7},"sk":{"a":0,"k":0,"ix":4},"sa":{"a":0,"k":0,"ix":5},"nm":"Transform"}],"nm":"Group 14","np":1,"cix":2,"bm":0,"ix":14,"mn":"ADBE Vector Group","hd":false},{"ty":"gr","it":[{"ty":"gr","it":[{"ind":0,"ty":"sh","ix":1,"ks":{"a":0,"k":{"i":[[0,0],[-1.011,-2.374],[-2.925,-0.003],[-0.094,0.987],[1.049,1.862],[1.136,2.075],[0.28,-0.971]],"o":[[-0.736,2.556],[0.991,2.327],[1.059,0.001],[0.215,-2.268],[-1.18,-2.094],[-0.506,-0.925],[0,0]],"v":[[-19.645,168.135],[-18.541,176.246],[-13.183,182.076],[-11.351,180.244],[-14.574,174.375],[-17.446,167.847],[-19.645,168.135]],"c":true},"ix":2},"nm":"Path 1","mn":"ADBE Vector Shape - Group","hd":false},{"ty":"fl","c":{"a":0,"k":[0.807843148708,0.349019616842,0.137254908681,1],"ix":4},"o":{"a":0,"k":100,"ix":5},"r":1,"bm":0,"nm":"Fill 1","mn":"ADBE Vector Graphic - Fill","hd":false},{"ty":"tr","p":{"a":0,"k":[0,0],"ix":2},"a":{"a":0,"k":[0,0],"ix":1},"s":{"a":0,"k":[100,100],"ix":3},"r":{"a":0,"k":0,"ix":6},"o":{"a":0,"k":100,"ix":7},"sk":{"a":0,"k":0,"ix":4},"sa":{"a":0,"k":0,"ix":5},"nm":"Transform"}],"nm":"Group 1","np":2,"cix":2,"bm":0,"ix":1,"mn":"ADBE Vector Group","hd":false},{"ty":"tr","p":{"a":0,"k":[0,0],"ix":2},"a":{"a":0,"k":[0,0],"ix":1},"s":{"a":0,"k":[100,100],"ix":3},"r":{"a":0,"k":0,"ix":6},"o":{"a":0,"k":100,"ix":7},"sk":{"a":0,"k":0,"ix":4},"sa":{"a":0,"k":0,"ix":5},"nm":"Transform"}],"nm":"Group 15","np":1,"cix":2,"bm":0,"ix":15,"mn":"ADBE Vector Group","hd":false},{"ty":"gr","it":[{"ty":"gr","it":[{"ind":0,"ty":"sh","ix":1,"ks":{"a":0,"k":{"i":[[0,0],[0.203,-1.483],[-0.172,1.152],[-0.22,1.478],[0.161,-1.176]],"o":[[-0.203,1.483],[-0.155,1.131],[0.22,-1.478],[0.175,-1.176],[0,0]],"v":[[57.366,168.843],[56.758,173.291],[58.498,173.771],[59.159,169.338],[57.366,168.843]],"c":true},"ix":2},"nm":"Path 1","mn":"ADBE Vector Shape - Group","hd":false},{"ty":"fl","c":{"a":0,"k":[0.807843148708,0.349019616842,0.137254908681,1],"ix":4},"o":{"a":0,"k":100,"ix":5},"r":1,"bm":0,"nm":"Fill 1","mn":"ADBE Vector Graphic - Fill","hd":false},{"ty":"tr","p":{"a":0,"k":[0,0],"ix":2},"a":{"a":0,"k":[0,0],"ix":1},"s":{"a":0,"k":[100,100],"ix":3},"r":{"a":0,"k":0,"ix":6},"o":{"a":0,"k":100,"ix":7},"sk":{"a":0,"k":0,"ix":4},"sa":{"a":0,"k":0,"ix":5},"nm":"Transform"}],"nm":"Group 1","np":2,"cix":2,"bm":0,"ix":1,"mn":"ADBE Vector Group","hd":false},{"ty":"tr","p":{"a":0,"k":[0,0],"ix":2},"a":{"a":0,"k":[0,0],"ix":1},"s":{"a":0,"k":[100,100],"ix":3},"r":{"a":0,"k":0,"ix":6},"o":{"a":0,"k":100,"ix":7},"sk":{"a":0,"k":0,"ix":4},"sa":{"a":0,"k":0,"ix":5},"nm":"Transform"}],"nm":"Group 16","np":1,"cix":2,"bm":0,"ix":16,"mn":"ADBE Vector Group","hd":false},{"ty":"gr","it":[{"ty":"gr","it":[{"ind":0,"ty":"sh","ix":1,"ks":{"a":0,"k":{"i":[[0,0],[-0.248,-4.197],[-0.253,1.61],[-0.157,4.332],[0.111,-1.815]],"o":[[-0.257,4.194],[0.085,1.439],[0.673,-4.286],[0.066,-1.838],[0,0]],"v":[[51.672,163.376],[51.109,176.065],[53.795,176.429],[54.516,163.376],[51.672,163.376]],"c":true},"ix":2},"nm":"Path 1","mn":"ADBE Vector Shape - Group","hd":false},{"ty":"fl","c":{"a":0,"k":[0.807843148708,0.349019616842,0.137254908681,1],"ix":4},"o":{"a":0,"k":100,"ix":5},"r":1,"bm":0,"nm":"Fill 1","mn":"ADBE Vector Graphic - Fill","hd":false},{"ty":"tr","p":{"a":0,"k":[0,0],"ix":2},"a":{"a":0,"k":[0,0],"ix":1},"s":{"a":0,"k":[100,100],"ix":3},"r":{"a":0,"k":0,"ix":6},"o":{"a":0,"k":100,"ix":7},"sk":{"a":0,"k":0,"ix":4},"sa":{"a":0,"k":0,"ix":5},"nm":"Transform"}],"nm":"Group 1","np":2,"cix":2,"bm":0,"ix":1,"mn":"ADBE Vector Group","hd":false},{"ty":"tr","p":{"a":0,"k":[0,0],"ix":2},"a":{"a":0,"k":[0,0],"ix":1},"s":{"a":0,"k":[100,100],"ix":3},"r":{"a":0,"k":0,"ix":6},"o":{"a":0,"k":100,"ix":7},"sk":{"a":0,"k":0,"ix":4},"sa":{"a":0,"k":0,"ix":5},"nm":"Transform"}],"nm":"Group 17","np":1,"cix":2,"bm":0,"ix":17,"mn":"ADBE Vector Group","hd":false},{"ty":"gr","it":[{"ty":"gr","it":[{"ind":0,"ty":"sh","ix":1,"ks":{"a":0,"k":{"i":[[0,0],[-0.036,-1.057],[-0.063,1.832],[-0.036,1.057],[-0.068,-1.974]],"o":[[0.036,1.057],[0.063,1.829],[0.036,-1.057],[0.068,-1.971],[0,0]],"v":[[70.053,143.714],[70.163,146.886],[73.007,146.886],[73.116,143.714],[70.053,143.714]],"c":true},"ix":2},"nm":"Path 1","mn":"ADBE Vector Shape - Group","hd":false},{"ty":"fl","c":{"a":0,"k":[1,0.698039233685,0.423529416323,1],"ix":4},"o":{"a":0,"k":100,"ix":5},"r":1,"bm":0,"nm":"Fill 1","mn":"ADBE Vector Graphic - Fill","hd":false},{"ty":"tr","p":{"a":0,"k":[0,0],"ix":2},"a":{"a":0,"k":[0,0],"ix":1},"s":{"a":0,"k":[100,100],"ix":3},"r":{"a":0,"k":0,"ix":6},"o":{"a":0,"k":100,"ix":7},"sk":{"a":0,"k":0,"ix":4},"sa":{"a":0,"k":0,"ix":5},"nm":"Transform"}],"nm":"Group 1","np":2,"cix":2,"bm":0,"ix":1,"mn":"ADBE Vector Group","hd":false},{"ty":"tr","p":{"a":0,"k":[0,0],"ix":2},"a":{"a":0,"k":[0,0],"ix":1},"s":{"a":0,"k":[100,100],"ix":3},"r":{"a":0,"k":0,"ix":6},"o":{"a":0,"k":100,"ix":7},"sk":{"a":0,"k":0,"ix":4},"sa":{"a":0,"k":0,"ix":5},"nm":"Transform"}],"nm":"Group 18","np":1,"cix":2,"bm":0,"ix":18,"mn":"ADBE Vector Group","hd":false},{"ty":"gr","it":[{"ty":"gr","it":[{"ind":0,"ty":"sh","ix":1,"ks":{"a":0,"k":{"i":[[0,0],[-0.363,-4.9],[-1.565,-3.869],[-0.611,2.334],[2.378,8.341],[-0.407,-2.519]],"o":[[0.784,4.851],[0.305,4.113],[0.773,1.912],[2.269,-8.671],[-0.729,-2.557],[0,0]],"v":[[65.845,107.453],[67.585,122.067],[69.446,134.159],[73.77,134.159],[69.747,106.377],[65.845,107.453]],"c":true},"ix":2},"nm":"Path 1","mn":"ADBE Vector Shape - Group","hd":false},{"ty":"fl","c":{"a":0,"k":[1,0.698039233685,0.423529416323,1],"ix":4},"o":{"a":0,"k":100,"ix":5},"r":1,"bm":0,"nm":"Fill 1","mn":"ADBE Vector Graphic - Fill","hd":false},{"ty":"tr","p":{"a":0,"k":[0,0],"ix":2},"a":{"a":0,"k":[0,0],"ix":1},"s":{"a":0,"k":[100,100],"ix":3},"r":{"a":0,"k":0,"ix":6},"o":{"a":0,"k":100,"ix":7},"sk":{"a":0,"k":0,"ix":4},"sa":{"a":0,"k":0,"ix":5},"nm":"Transform"}],"nm":"Group 1","np":2,"cix":2,"bm":0,"ix":1,"mn":"ADBE Vector Group","hd":false},{"ty":"tr","p":{"a":0,"k":[0,0],"ix":2},"a":{"a":0,"k":[0,0],"ix":1},"s":{"a":0,"k":[100,100],"ix":3},"r":{"a":0,"k":0,"ix":6},"o":{"a":0,"k":100,"ix":7},"sk":{"a":0,"k":0,"ix":4},"sa":{"a":0,"k":0,"ix":5},"nm":"Transform"}],"nm":"Group 19","np":1,"cix":2,"bm":0,"ix":19,"mn":"ADBE Vector Group","hd":false},{"ty":"gr","it":[{"ty":"gr","it":[{"ind":0,"ty":"sh","ix":1,"ks":{"a":0,"k":{"i":[[0,0],[0,-0.485],[-0.328,-0.73],[-0.579,-0.488],[-1.024,0.282],[-0.376,0.933],[-0.079,0.221],[0.033,0.521],[0.254,0.603],[0.428,0.463],[0.609,-2.282]],"o":[[-0.125,0.467],[0,0.82],[0.318,0.708],[0.779,0.656],[1.021,-0.281],[0.088,-0.218],[0.176,-0.495],[-0.041,-0.656],[-0.248,-0.588],[-1.657,-1.794],[0,0]],"v":[[45.491,102.925],[45.229,104.369],[45.865,106.612],[47.259,108.294],[49.972,109.011],[51.92,107.063],[52.185,106.408],[52.346,104.857],[51.962,103.013],[50.884,101.501],[45.491,102.925]],"c":true},"ix":2},"nm":"Path 1","mn":"ADBE Vector Shape - Group","hd":false},{"ty":"fl","c":{"a":0,"k":[1,0.698039233685,0.423529416323,1],"ix":4},"o":{"a":0,"k":100,"ix":5},"r":1,"bm":0,"nm":"Fill 1","mn":"ADBE Vector Graphic - Fill","hd":false},{"ty":"tr","p":{"a":0,"k":[0,0],"ix":2},"a":{"a":0,"k":[0,0],"ix":1},"s":{"a":0,"k":[100,100],"ix":3},"r":{"a":0,"k":0,"ix":6},"o":{"a":0,"k":100,"ix":7},"sk":{"a":0,"k":0,"ix":4},"sa":{"a":0,"k":0,"ix":5},"nm":"Transform"}],"nm":"Group 1","np":2,"cix":2,"bm":0,"ix":1,"mn":"ADBE Vector Group","hd":false},{"ty":"tr","p":{"a":0,"k":[0,0],"ix":2},"a":{"a":0,"k":[0,0],"ix":1},"s":{"a":0,"k":[100,100],"ix":3},"r":{"a":0,"k":0,"ix":6},"o":{"a":0,"k":100,"ix":7},"sk":{"a":0,"k":0,"ix":4},"sa":{"a":0,"k":0,"ix":5},"nm":"Transform"}],"nm":"Group 20","np":1,"cix":2,"bm":0,"ix":20,"mn":"ADBE Vector Group","hd":false},{"ty":"gr","it":[{"ty":"gr","it":[{"ind":0,"ty":"sh","ix":1,"ks":{"a":0,"k":{"i":[[0,0],[-0.123,-0.812],[-0.143,0.94],[-0.123,0.812],[0.959,0],[-0.131,-0.864]],"o":[[0.123,0.812],[0.142,0.94],[0.123,-0.812],[0.131,-0.863],[-0.951,0],[0,0]],"v":[[9.998,106.014],[10.367,108.449],[12.266,108.449],[12.635,106.014],[11.316,104.283],[9.998,106.014]],"c":true},"ix":2},"nm":"Path 1","mn":"ADBE Vector Shape - Group","hd":false},{"ty":"fl","c":{"a":0,"k":[1,0.698039233685,0.423529416323,1],"ix":4},"o":{"a":0,"k":100,"ix":5},"r":1,"bm":0,"nm":"Fill 1","mn":"ADBE Vector Graphic - Fill","hd":false},{"ty":"tr","p":{"a":0,"k":[0,0],"ix":2},"a":{"a":0,"k":[0,0],"ix":1},"s":{"a":0,"k":[100,100],"ix":3},"r":{"a":0,"k":0,"ix":6},"o":{"a":0,"k":100,"ix":7},"sk":{"a":0,"k":0,"ix":4},"sa":{"a":0,"k":0,"ix":5},"nm":"Transform"}],"nm":"Group 1","np":2,"cix":2,"bm":0,"ix":1,"mn":"ADBE Vector Group","hd":false},{"ty":"tr","p":{"a":0,"k":[0,0],"ix":2},"a":{"a":0,"k":[0,0],"ix":1},"s":{"a":0,"k":[100,100],"ix":3},"r":{"a":0,"k":0,"ix":6},"o":{"a":0,"k":100,"ix":7},"sk":{"a":0,"k":0,"ix":4},"sa":{"a":0,"k":0,"ix":5},"nm":"Transform"}],"nm":"Group 21","np":1,"cix":2,"bm":0,"ix":21,"mn":"ADBE Vector Group","hd":false},{"ty":"gr","it":[{"ty":"gr","it":[{"ind":0,"ty":"sh","ix":1,"ks":{"a":0,"k":{"i":[[0,0],[0.945,-1.494],[-0.091,-1.991],[-1.515,-0.609],[-1.005,1.243],[-0.509,1.891],[0.085,1.613],[2.05,-1.073]],"o":[[-1.608,0.842],[-1.034,1.635],[0.073,1.594],[1.359,0.546],[1.271,-1.573],[0.412,-1.528],[-0.121,-2.292],[0,0]],"v":[[-2.801,102.144],[-6.317,106.06],[-8.299,111.47],[-5.845,115.118],[-1.484,114.293],[0.656,109.304],[1.663,104.706],[-2.801,102.144]],"c":true},"ix":2},"nm":"Path 1","mn":"ADBE Vector Shape - Group","hd":false},{"ty":"fl","c":{"a":0,"k":[1,0.698039233685,0.423529416323,1],"ix":4},"o":{"a":0,"k":100,"ix":5},"r":1,"bm":0,"nm":"Fill 1","mn":"ADBE Vector Graphic - Fill","hd":false},{"ty":"tr","p":{"a":0,"k":[0,0],"ix":2},"a":{"a":0,"k":[0,0],"ix":1},"s":{"a":0,"k":[100,100],"ix":3},"r":{"a":0,"k":0,"ix":6},"o":{"a":0,"k":100,"ix":7},"sk":{"a":0,"k":0,"ix":4},"sa":{"a":0,"k":0,"ix":5},"nm":"Transform"}],"nm":"Group 1","np":2,"cix":2,"bm":0,"ix":1,"mn":"ADBE Vector Group","hd":false},{"ty":"tr","p":{"a":0,"k":[0,0],"ix":2},"a":{"a":0,"k":[0,0],"ix":1},"s":{"a":0,"k":[100,100],"ix":3},"r":{"a":0,"k":0,"ix":6},"o":{"a":0,"k":100,"ix":7},"sk":{"a":0,"k":0,"ix":4},"sa":{"a":0,"k":0,"ix":5},"nm":"Transform"}],"nm":"Group 22","np":1,"cix":2,"bm":0,"ix":22,"mn":"ADBE Vector Group","hd":false},{"ty":"gr","it":[{"ty":"gr","it":[{"ind":0,"ty":"sh","ix":1,"ks":{"a":0,"k":{"i":[[0,0],[0.293,-1.464],[-0.153,-1.401],[-0.506,1.099],[-0.349,2.79],[0.235,-1.173]],"o":[[-0.293,1.464],[-0.274,1.367],[0.103,0.947],[1.185,-2.575],[0.149,-1.188],[0,0]],"v":[[-48.812,132.63],[-49.692,137.02],[-50.216,141.149],[-48.177,141.701],[-46.717,132.913],[-48.812,132.63]],"c":true},"ix":2},"nm":"Path 1","mn":"ADBE Vector Shape - Group","hd":false},{"ty":"fl","c":{"a":0,"k":[1,0.698039233685,0.423529416323,1],"ix":4},"o":{"a":0,"k":100,"ix":5},"r":1,"bm":0,"nm":"Fill 1","mn":"ADBE Vector Graphic - Fill","hd":false},{"ty":"tr","p":{"a":0,"k":[0,0],"ix":2},"a":{"a":0,"k":[0,0],"ix":1},"s":{"a":0,"k":[100,100],"ix":3},"r":{"a":0,"k":0,"ix":6},"o":{"a":0,"k":100,"ix":7},"sk":{"a":0,"k":0,"ix":4},"sa":{"a":0,"k":0,"ix":5},"nm":"Transform"}],"nm":"Group 1","np":2,"cix":2,"bm":0,"ix":1,"mn":"ADBE Vector Group","hd":false},{"ty":"tr","p":{"a":0,"k":[0,0],"ix":2},"a":{"a":0,"k":[0,0],"ix":1},"s":{"a":0,"k":[100,100],"ix":3},"r":{"a":0,"k":0,"ix":6},"o":{"a":0,"k":100,"ix":7},"sk":{"a":0,"k":0,"ix":4},"sa":{"a":0,"k":0,"ix":5},"nm":"Transform"}],"nm":"Group 23","np":1,"cix":2,"bm":0,"ix":23,"mn":"ADBE Vector Group","hd":false},{"ty":"gr","it":[{"ty":"gr","it":[{"ind":0,"ty":"sh","ix":1,"ks":{"a":0,"k":{"i":[[0,0],[0.574,-6.342],[-0.774,1.238],[-3.518,4.236],[1.724,-1.672]],"o":[[-4.468,4.333],[-0.15,1.652],[2.894,-4.631],[1.484,-1.786],[0,0]],"v":[[-38.086,108.898],[-46.932,124.618],[-43.977,125.418],[-35.495,111.489],[-38.086,108.898]],"c":true},"ix":2},"nm":"Path 1","mn":"ADBE Vector Shape - Group","hd":false},{"ty":"fl","c":{"a":0,"k":[1,0.698039233685,0.423529416323,1],"ix":4},"o":{"a":0,"k":100,"ix":5},"r":1,"bm":0,"nm":"Fill 1","mn":"ADBE Vector Graphic - Fill","hd":false},{"ty":"tr","p":{"a":0,"k":[0,0],"ix":2},"a":{"a":0,"k":[0,0],"ix":1},"s":{"a":0,"k":[100,100],"ix":3},"r":{"a":0,"k":0,"ix":6},"o":{"a":0,"k":100,"ix":7},"sk":{"a":0,"k":0,"ix":4},"sa":{"a":0,"k":0,"ix":5},"nm":"Transform"}],"nm":"Group 1","np":2,"cix":2,"bm":0,"ix":1,"mn":"ADBE Vector Group","hd":false},{"ty":"tr","p":{"a":0,"k":[0,0],"ix":2},"a":{"a":0,"k":[0,0],"ix":1},"s":{"a":0,"k":[100,100],"ix":3},"r":{"a":0,"k":0,"ix":6},"o":{"a":0,"k":100,"ix":7},"sk":{"a":0,"k":0,"ix":4},"sa":{"a":0,"k":0,"ix":5},"nm":"Transform"}],"nm":"Group 24","np":1,"cix":2,"bm":0,"ix":24,"mn":"ADBE Vector Group","hd":false},{"ty":"gr","it":[{"ty":"gr","it":[{"ind":0,"ty":"sh","ix":1,"ks":{"a":0,"k":{"i":[[0,0],[-0.392,13.133],[0.353,-1.339],[-6.176,-11.689],[0.346,0.909]],"o":[[-4.732,-12.427],[0.042,-1.391],[-3.43,13.01],[0.44,0.833],[0,0]],"v":[[10.578,181.089],[5.599,143.199],[3.182,142.872],[9.029,181.743],[10.578,181.089]],"c":true},"ix":2},"nm":"Path 1","mn":"ADBE Vector Shape - Group","hd":false},{"ty":"fl","c":{"a":0,"k":[0.807843148708,0.349019616842,0.137254908681,1],"ix":4},"o":{"a":0,"k":100,"ix":5},"r":1,"bm":0,"nm":"Fill 1","mn":"ADBE Vector Graphic - Fill","hd":false},{"ty":"tr","p":{"a":0,"k":[0,0],"ix":2},"a":{"a":0,"k":[0,0],"ix":1},"s":{"a":0,"k":[100,100],"ix":3},"r":{"a":0,"k":0,"ix":6},"o":{"a":0,"k":100,"ix":7},"sk":{"a":0,"k":0,"ix":4},"sa":{"a":0,"k":0,"ix":5},"nm":"Transform"}],"nm":"Group 1","np":2,"cix":2,"bm":0,"ix":1,"mn":"ADBE Vector Group","hd":false},{"ty":"tr","p":{"a":0,"k":[0,0],"ix":2},"a":{"a":0,"k":[0,0],"ix":1},"s":{"a":0,"k":[100,100],"ix":3},"r":{"a":0,"k":0,"ix":6},"o":{"a":0,"k":100,"ix":7},"sk":{"a":0,"k":0,"ix":4},"sa":{"a":0,"k":0,"ix":5},"nm":"Transform"}],"nm":"Group 25","np":1,"cix":2,"bm":0,"ix":25,"mn":"ADBE Vector Group","hd":false},{"ty":"gr","it":[{"ty":"gr","it":[{"ind":0,"ty":"sh","ix":1,"ks":{"a":0,"k":{"i":[[0,0],[-0.756,-10.298],[-0.263,1.722],[-1.333,10.42],[0.236,-1.428]],"o":[[-1.677,10.145],[0.111,1.509],[1.582,-10.354],[0.182,-1.424],[0,0]],"v":[[4.754,105.817],[1.666,137.194],[4.513,137.58],[7.278,106.159],[4.754,105.817]],"c":true},"ix":2},"nm":"Path 1","mn":"ADBE Vector Shape - Group","hd":false},{"ty":"fl","c":{"a":0,"k":[0.807843148708,0.349019616842,0.137254908681,1],"ix":4},"o":{"a":0,"k":100,"ix":5},"r":1,"bm":0,"nm":"Fill 1","mn":"ADBE Vector Graphic - Fill","hd":false},{"ty":"tr","p":{"a":0,"k":[0,0],"ix":2},"a":{"a":0,"k":[0,0],"ix":1},"s":{"a":0,"k":[100,100],"ix":3},"r":{"a":0,"k":0,"ix":6},"o":{"a":0,"k":100,"ix":7},"sk":{"a":0,"k":0,"ix":4},"sa":{"a":0,"k":0,"ix":5},"nm":"Transform"}],"nm":"Group 1","np":2,"cix":2,"bm":0,"ix":1,"mn":"ADBE Vector Group","hd":false},{"ty":"tr","p":{"a":0,"k":[0,0],"ix":2},"a":{"a":0,"k":[0,0],"ix":1},"s":{"a":0,"k":[100,100],"ix":3},"r":{"a":0,"k":0,"ix":6},"o":{"a":0,"k":100,"ix":7},"sk":{"a":0,"k":0,"ix":4},"sa":{"a":0,"k":0,"ix":5},"nm":"Transform"}],"nm":"Group 26","np":1,"cix":2,"bm":0,"ix":26,"mn":"ADBE Vector Group","hd":false},{"ty":"gr","it":[{"ty":"gr","it":[{"ind":0,"ty":"sh","ix":1,"ks":{"a":0,"k":{"i":[[0,0],[1.704,13.328],[0.143,-1.903],[1.49,-13.408],[-0.328,1.221]],"o":[[3.459,-12.871],[-0.233,-1.82],[-1.009,13.444],[-0.145,1.307],[0,0]],"v":[[40.961,178.821],[45.158,138.348],[42.259,138.348],[38.706,178.516],[40.961,178.821]],"c":true},"ix":2},"nm":"Path 1","mn":"ADBE Vector Shape - Group","hd":false},{"ty":"fl","c":{"a":0,"k":[0.807843148708,0.349019616842,0.137254908681,1],"ix":4},"o":{"a":0,"k":100,"ix":5},"r":1,"bm":0,"nm":"Fill 1","mn":"ADBE Vector Graphic - Fill","hd":false},{"ty":"tr","p":{"a":0,"k":[0,0],"ix":2},"a":{"a":0,"k":[0,0],"ix":1},"s":{"a":0,"k":[100,100],"ix":3},"r":{"a":0,"k":0,"ix":6},"o":{"a":0,"k":100,"ix":7},"sk":{"a":0,"k":0,"ix":4},"sa":{"a":0,"k":0,"ix":5},"nm":"Transform"}],"nm":"Group 1","np":2,"cix":2,"bm":0,"ix":1,"mn":"ADBE Vector Group","hd":false},{"ty":"tr","p":{"a":0,"k":[0,0],"ix":2},"a":{"a":0,"k":[0,0],"ix":1},"s":{"a":0,"k":[100,100],"ix":3},"r":{"a":0,"k":0,"ix":6},"o":{"a":0,"k":100,"ix":7},"sk":{"a":0,"k":0,"ix":4},"sa":{"a":0,"k":0,"ix":5},"nm":"Transform"}],"nm":"Group 27","np":1,"cix":2,"bm":0,"ix":27,"mn":"ADBE Vector Group","hd":false},{"ty":"gr","it":[{"ty":"gr","it":[{"ind":0,"ty":"sh","ix":1,"ks":{"a":0,"k":{"i":[[0,0],[-0.999,-9.593],[-0.418,1.814],[4.499,8.37],[-0.265,-1.008]],"o":[[2.497,9.495],[0.166,1.596],[2.132,-9.25],[-0.505,-0.94],[0,0]],"v":[[40.372,103.709],[42.874,132.079],[45.882,132.486],[42.071,102.992],[40.372,103.709]],"c":true},"ix":2},"nm":"Path 1","mn":"ADBE Vector Shape - Group","hd":false},{"ty":"fl","c":{"a":0,"k":[0.807843148708,0.349019616842,0.137254908681,1],"ix":4},"o":{"a":0,"k":100,"ix":5},"r":1,"bm":0,"nm":"Fill 1","mn":"ADBE Vector Graphic - Fill","hd":false},{"ty":"tr","p":{"a":0,"k":[0,0],"ix":2},"a":{"a":0,"k":[0,0],"ix":1},"s":{"a":0,"k":[100,100],"ix":3},"r":{"a":0,"k":0,"ix":6},"o":{"a":0,"k":100,"ix":7},"sk":{"a":0,"k":0,"ix":4},"sa":{"a":0,"k":0,"ix":5},"nm":"Transform"}],"nm":"Group 1","np":2,"cix":2,"bm":0,"ix":1,"mn":"ADBE Vector Group","hd":false},{"ty":"tr","p":{"a":0,"k":[0,0],"ix":2},"a":{"a":0,"k":[0,0],"ix":1},"s":{"a":0,"k":[100,100],"ix":3},"r":{"a":0,"k":0,"ix":6},"o":{"a":0,"k":100,"ix":7},"sk":{"a":0,"k":0,"ix":4},"sa":{"a":0,"k":0,"ix":5},"nm":"Transform"}],"nm":"Group 28","np":1,"cix":2,"bm":0,"ix":28,"mn":"ADBE Vector Group","hd":false},{"ty":"gr","it":[{"ty":"gr","it":[{"ind":0,"ty":"sh","ix":1,"ks":{"a":0,"k":{"i":[[0,0],[0.884,9.247],[0.012,-1.147],[-5.418,-7.908],[0.511,0.858]],"o":[[-4.686,-7.875],[-0.105,-1.101],[-0.099,9.855],[0.55,0.803],[0,0]],"v":[[-21.359,179.961],[-31.309,154.083],[-33.059,154.083],[-22.682,180.734],[-21.359,179.961]],"c":true},"ix":2},"nm":"Path 1","mn":"ADBE Vector Shape - Group","hd":false},{"ty":"fl","c":{"a":0,"k":[0.807843148708,0.349019616842,0.137254908681,1],"ix":4},"o":{"a":0,"k":100,"ix":5},"r":1,"bm":0,"nm":"Fill 1","mn":"ADBE Vector Graphic - Fill","hd":false},{"ty":"tr","p":{"a":0,"k":[0,0],"ix":2},"a":{"a":0,"k":[0,0],"ix":1},"s":{"a":0,"k":[100,100],"ix":3},"r":{"a":0,"k":0,"ix":6},"o":{"a":0,"k":100,"ix":7},"sk":{"a":0,"k":0,"ix":4},"sa":{"a":0,"k":0,"ix":5},"nm":"Transform"}],"nm":"Group 1","np":2,"cix":2,"bm":0,"ix":1,"mn":"ADBE Vector Group","hd":false},{"ty":"tr","p":{"a":0,"k":[0,0],"ix":2},"a":{"a":0,"k":[0,0],"ix":1},"s":{"a":0,"k":[100,100],"ix":3},"r":{"a":0,"k":0,"ix":6},"o":{"a":0,"k":100,"ix":7},"sk":{"a":0,"k":0,"ix":4},"sa":{"a":0,"k":0,"ix":5},"nm":"Transform"}],"nm":"Group 29","np":1,"cix":2,"bm":0,"ix":29,"mn":"ADBE Vector Group","hd":false},{"ty":"gr","it":[{"ty":"gr","it":[{"ind":0,"ty":"sh","ix":1,"ks":{"a":0,"k":{"i":[[0,0],[-2.226,-12.812],[0.026,1.004],[-4.877,11.508],[0.458,-0.935]],"o":[[-5.67,11.58],[0.175,1.009],[-0.325,-12.405],[0.388,-0.914],[0,0]],"v":[[-27.916,108.498],[-34.151,145.609],[-32.379,145.369],[-26.547,109.299],[-27.916,108.498]],"c":true},"ix":2},"nm":"Path 1","mn":"ADBE Vector Shape - Group","hd":false},{"ty":"fl","c":{"a":0,"k":[0.807843148708,0.349019616842,0.137254908681,1],"ix":4},"o":{"a":0,"k":100,"ix":5},"r":1,"bm":0,"nm":"Fill 1","mn":"ADBE Vector Graphic - Fill","hd":false},{"ty":"tr","p":{"a":0,"k":[0,0],"ix":2},"a":{"a":0,"k":[0,0],"ix":1},"s":{"a":0,"k":[100,100],"ix":3},"r":{"a":0,"k":0,"ix":6},"o":{"a":0,"k":100,"ix":7},"sk":{"a":0,"k":0,"ix":4},"sa":{"a":0,"k":0,"ix":5},"nm":"Transform"}],"nm":"Group 1","np":2,"cix":2,"bm":0,"ix":1,"mn":"ADBE Vector Group","hd":false},{"ty":"tr","p":{"a":0,"k":[0,0],"ix":2},"a":{"a":0,"k":[0,0],"ix":1},"s":{"a":0,"k":[100,100],"ix":3},"r":{"a":0,"k":0,"ix":6},"o":{"a":0,"k":100,"ix":7},"sk":{"a":0,"k":0,"ix":4},"sa":{"a":0,"k":0,"ix":5},"nm":"Transform"}],"nm":"Group 30","np":1,"cix":2,"bm":0,"ix":30,"mn":"ADBE Vector Group","hd":false},{"ty":"gr","it":[{"ind":0,"ty":"sh","ix":1,"ks":{"a":0,"k":{"i":[[4.507,10.922],[4.927,0.469],[3.152,6.897],[-18.182,19.688],[-3.722,0.773],[-1.087,-3.643],[-9.102,-9.285],[-8.76,-6.22],[-1.377,-0.119],[-1.507,0.905],[-5.946,-6.72],[-0.987,-8.919],[0.845,-8.301],[7.411,-7.544],[8.129,6.764],[6.178,-0.603],[3.346,5.229]],"o":[[-1.515,7.782],[-7.58,-0.722],[-10.775,-23.584],[2.579,-2.793],[3.722,-0.773],[7.585,-10.56],[6.537,-8.526],[1.127,0.8],[1.751,0.151],[7.692,-4.62],[5.946,6.72],[0.918,8.293],[-1.071,10.521],[-7.411,7.544],[-2.272,5.777],[-6.178,0.603],[-7.763,8.907]],"v":[[-19.209,181.038],[-33.628,189.758],[-52.399,174.507],[-44.656,103.648],[-34.097,96.844],[-24.853,102.257],[9.3,99.646],[38.136,95.3],[41.777,97.167],[46.56,95.197],[70.768,100.594],[79.912,125.452],[80.021,150.436],[68.75,179.436],[40.094,182.909],[25.968,193.575],[10.046,185.841]],"c":true},"ix":2},"nm":"Path 1","mn":"ADBE Vector Shape - Group","hd":false},{"ty":"fl","c":{"a":0,"k":[0.850980401039,0.498039215803,0.152941182256,1],"ix":4},"o":{"a":0,"k":100,"ix":5},"r":1,"bm":0,"nm":"Fill 1","mn":"ADBE Vector Graphic - Fill","hd":false},{"ty":"tr","p":{"a":0,"k":[0,0],"ix":2},"a":{"a":0,"k":[0,0],"ix":1},"s":{"a":0,"k":[100,100],"ix":3},"r":{"a":0,"k":0,"ix":6},"o":{"a":0,"k":100,"ix":7},"sk":{"a":0,"k":0,"ix":4},"sa":{"a":0,"k":0,"ix":5},"nm":"Transform"}],"nm":"Group 31","np":2,"cix":2,"bm":0,"ix":31,"mn":"ADBE Vector Group","hd":false},{"ty":"gr","it":[{"ind":0,"ty":"sh","ix":1,"ks":{"a":0,"k":{"i":[[0,0],[-4.157,5.421],[-0.718,0.801],[-3.185,2.94],[0.489,1.471],[0.062,0.047],[1.119,-0.739],[1.341,-0.017],[-1.536,2.124],[-1.538,1.025],[-3.249,-0.448],[-0.451,-4.212],[0.967,-4.124],[-0.413,-1.375],[-0.405,-0.383],[0.225,-2.558],[18.081,-1.713]],"o":[[2.304,-4.093],[0.769,-1.003],[3.247,-3.621],[1.623,-1.498],[-0.21,-0.632],[-1.071,-0.807],[-1.119,0.739],[-2.63,0.033],[1.091,-1.508],[2.73,-1.818],[4.196,0.579],[0.451,4.212],[-0.328,1.398],[0.476,1.587],[2.899,2.743],[-0.188,2.139],[0,0]],"v":[[-13.966,100.077],[-3.234,83.23],[-1.301,80.844],[7.065,73.103],[9.308,68.653],[8.521,67.641],[4.783,68.102],[1.216,69.82],[-1.345,64.901],[3.299,60.881],[12.36,57.669],[19.82,66.795],[18,79.302],[17.797,83.552],[19.728,86.497],[28.567,97.629],[5.422,103.851]],"c":false},"ix":2},"nm":"Path 1","mn":"ADBE Vector Shape - Group","hd":false},{"ty":"fl","c":{"a":0,"k":[0.454901963472,0.517647087574,0.333333343267,1],"ix":4},"o":{"a":0,"k":100,"ix":5},"r":1,"bm":0,"nm":"Fill 1","mn":"ADBE Vector Graphic - Fill","hd":false},{"ty":"tr","p":{"a":0,"k":[0,0],"ix":2},"a":{"a":0,"k":[0,0],"ix":1},"s":{"a":0,"k":[100,100],"ix":3},"r":{"a":0,"k":0,"ix":6},"o":{"a":0,"k":100,"ix":7},"sk":{"a":0,"k":0,"ix":4},"sa":{"a":0,"k":0,"ix":5},"nm":"Transform"}],"nm":"Group 32","np":2,"cix":2,"bm":0,"ix":32,"mn":"ADBE Vector Group","hd":false}],"ip":0,"op":30,"st":0,"bm":0}]}],"layers":[{"ddd":0,"ind":1,"ty":0,"nm":"Pre-comp 1","refId":"comp_0","sr":1,"ks":{"o":{"a":0,"k":100,"ix":11},"r":{"a":1,"k":[{"i":{"x":[0.667],"y":[1]},"o":{"x":[0.333],"y":[0]},"t":76,"s":[0]},{"i":{"x":[0.667],"y":[1]},"o":{"x":[0.333],"y":[0]},"t":87,"s":[-46.85]},{"i":{"x":[0.667],"y":[1]},"o":{"x":[0.167],"y":[0]},"t":97,"s":[37.207]},{"i":{"x":[0.667],"y":[1]},"o":{"x":[0.167],"y":[0]},"t":114,"s":[-19.984]},{"t":132,"s":[16.084]}],"ix":10},"p":{"a":1,"k":[{"i":{"x":0.667,"y":1},"o":{"x":0.333,"y":0},"t":68,"s":[250,250,0],"to":[0,0,0],"ti":[0,0,0]},{"i":{"x":0.667,"y":1},"o":{"x":0.333,"y":0},"t":76,"s":[108,588,0],"to":[0,0,0],"ti":[0,0,0]},{"i":{"x":0.667,"y":0.813},"o":{"x":0.333,"y":0},"t":87,"s":[310,348,0],"to":[0,0,0],"ti":[0,0,0]},{"i":{"x":0.667,"y":1},"o":{"x":0.333,"y":0.365},"t":97,"s":[167.085,249.626,0],"to":[0,0,0],"ti":[0,0,0]},{"t":104,"s":[228,262,0]}],"ix":2,"l":2},"a":{"a":0,"k":[500,500,0],"ix":1,"l":2},"s":{"a":1,"k":[{"i":{"x":[0.667,0.667,0.667],"y":[1,1,1]},"o":{"x":[0.333,0.333,0.333],"y":[0,0,0]},"t":37,"s":[100,100,100]},{"i":{"x":[0.667,0.667,0.667],"y":[1,1,1]},"o":{"x":[0.333,0.333,0.333],"y":[0,0,0]},"t":47,"s":[39,39,100]},{"i":{"x":[0.667,0.667,0.667],"y":[1,1,1]},"o":{"x":[0.333,0.333,0.333],"y":[0,0,0]},"t":68,"s":[39,39,100]},{"i":{"x":[0.667,0.667,0.667],"y":[1,1,1]},"o":{"x":[0.167,0.167,0.167],"y":[0,0,0]},"t":76,"s":[255.6,255.6,100]},{"i":{"x":[0.667,0.667,0.667],"y":[1,1,1]},"o":{"x":[0.167,0.167,0.167],"y":[0,0,0]},"t":87,"s":[255.6,255.6,100]},{"t":104,"s":[100,100,100]}],"ix":6,"l":2}},"ao":0,"w":1000,"h":1000,"ip":0,"op":144,"st":0,"bm":0},{"ddd":0,"ind":2,"ty":4,"nm":"Shape Layer 1","sr":1,"ks":{"o":{"a":0,"k":100,"ix":11},"r":{"a":0,"k":0,"ix":10},"p":{"a":0,"k":[250,250,0],"ix":2,"l":2},"a":{"a":0,"k":[0,0,0],"ix":1,"l":2},"s":{"a":0,"k":[100,100,100],"ix":6,"l":2}},"ao":0,"shapes":[{"ty":"gr","it":[{"ty":"rc","d":1,"s":{"a":0,"k":[1097.812,972.203],"ix":2},"p":{"a":0,"k":[0,0],"ix":3},"r":{"a":0,"k":0,"ix":4},"nm":"Rectangle Path 1","mn":"ADBE Vector Shape - Rect","hd":false},{"ty":"st","c":{"a":0,"k":[0.236396998985,0.900829958448,1,1],"ix":3},"o":{"a":0,"k":100,"ix":4},"w":{"a":0,"k":0,"ix":5},"lc":1,"lj":1,"ml":4,"bm":0,"nm":"Stroke 1","mn":"ADBE Vector Graphic - Stroke","hd":false},{"ty":"fl","c":{"a":0,"k":[0,0,0,1],"ix":4},"o":{"a":0,"k":100,"ix":5},"r":1,"bm":0,"nm":"Fill 1","mn":"ADBE Vector Graphic - Fill","hd":false},{"ty":"tr","p":{"a":0,"k":[90.906,36.102],"ix":2},"a":{"a":0,"k":[0,0],"ix":1},"s":{"a":0,"k":[100,100],"ix":3},"r":{"a":0,"k":0,"ix":6},"o":{"a":0,"k":100,"ix":7},"sk":{"a":0,"k":0,"ix":4},"sa":{"a":0,"k":0,"ix":5},"nm":"Transform"}],"nm":"Rectangle 1","np":3,"cix":2,"bm":0,"ix":1,"mn":"ADBE Vector Group","hd":false}],"ip":0,"op":144,"st":0,"bm":0}],"markers":[]}